{"v":"5.5.2","fr":29.9700012207031,"ip":0,"op":69.0000028104276,"w":380,"h":240,"nm":"main-tag-illustration","ddd":0,"assets":[],"layers":[{"ddd":0,"ind":1,"ty":4,"nm":"Pizza Outlines","sr":1,"ks":{"o":{"a":0,"k":100,"ix":11},"r":{"a":0,"k":0,"ix":10},"p":{"a":0,"k":[280.419,98.974,0],"ix":2},"a":{"a":0,"k":[42.267,11.214,0],"ix":1},"s":{"a":1,"k":[{"i":{"x":[0.667,0.667,0.667],"y":[1,1,1]},"o":{"x":[0.333,0.333,0.333],"y":[0,0,0]},"t":47,"s":[0,0,100]},{"i":{"x":[0.667,0.667,0.667],"y":[1,1,1]},"o":{"x":[0.333,0.333,0.333],"y":[0,0,0]},"t":62,"s":[100,127,100]},{"t":71.0000028918893,"s":[100,100,100]}],"ix":6}},"ao":0,"shapes":[{"ty":"gr","it":[{"ind":0,"ty":"sh","ix":1,"ks":{"a":0,"k":{"i":[[-9.706,-2.241],[0.245,-2.097],[2.414,1.559]],"o":[[0,0],[-0.245,2.098],[-2.415,-1.558]],"v":[[1.544,-2.148],[7.917,1.583],[-0.243,2.831]],"c":true},"ix":2},"nm":"Path 1","mn":"ADBE Vector Shape - Group","hd":false},{"ty":"fl","c":{"a":0,"k":[0.972463809743,0.180861259909,0.012286408742,1],"ix":4},"o":{"a":0,"k":100,"ix":5},"r":1,"bm":0,"nm":"Fill 1","mn":"ADBE Vector Graphic - Fill","hd":false},{"ty":"tr","p":{"a":0,"k":[65.753,32.95],"ix":2},"a":{"a":0,"k":[0,0],"ix":1},"s":{"a":0,"k":[100,100],"ix":3},"r":{"a":0,"k":0,"ix":6},"o":{"a":0,"k":100,"ix":7},"sk":{"a":0,"k":0,"ix":4},"sa":{"a":0,"k":0,"ix":5},"nm":"Transform"}],"nm":"Group 1","np":4,"cix":2,"bm":0,"ix":1,"mn":"ADBE Vector Group","hd":false},{"ty":"gr","it":[{"ind":0,"ty":"sh","ix":1,"ks":{"a":0,"k":{"i":[[-3.091,1.421],[2.094,-1.231],[2.314,1.676],[-3.788,-0.945]],"o":[[0,0],[-2.093,1.231],[-2.316,-1.676],[3.788,0.944]],"v":[[4.225,-1.478],[6.276,3.156],[-4.047,1.029],[-4.582,-3.443]],"c":true},"ix":2},"nm":"Path 1","mn":"ADBE Vector Shape - Group","hd":false},{"ty":"fl","c":{"a":0,"k":[0.972463809743,0.180861259909,0.012286408742,1],"ix":4},"o":{"a":0,"k":100,"ix":5},"r":1,"bm":0,"nm":"Fill 1","mn":"ADBE Vector Graphic - Fill","hd":false},{"ty":"tr","p":{"a":0,"k":[49.919,27.053],"ix":2},"a":{"a":0,"k":[0,0],"ix":1},"s":{"a":0,"k":[100,100],"ix":3},"r":{"a":0,"k":0,"ix":6},"o":{"a":0,"k":100,"ix":7},"sk":{"a":0,"k":0,"ix":4},"sa":{"a":0,"k":0,"ix":5},"nm":"Transform"}],"nm":"Group 2","np":4,"cix":2,"bm":0,"ix":2,"mn":"ADBE Vector Group","hd":false},{"ty":"gr","it":[{"ind":0,"ty":"sh","ix":1,"ks":{"a":0,"k":{"i":[[-12.569,-1.433],[-1.856,-1.637],[2.495,0.555]],"o":[[0,0],[1.858,1.636],[-2.496,-0.556]],"v":[[0.428,-2.299],[10.283,0.865],[7.552,3.176]],"c":true},"ix":2},"nm":"Path 1","mn":"ADBE Vector Shape - Group","hd":false},{"ty":"fl","c":{"a":0,"k":[0.972463809743,0.180861259909,0.012286408742,1],"ix":4},"o":{"a":0,"k":100,"ix":5},"r":1,"bm":0,"nm":"Fill 1","mn":"ADBE Vector Graphic - Fill","hd":false},{"ty":"tr","p":{"a":0,"k":[52.978,21.481],"ix":2},"a":{"a":0,"k":[0,0],"ix":1},"s":{"a":0,"k":[100,100],"ix":3},"r":{"a":0,"k":0,"ix":6},"o":{"a":0,"k":100,"ix":7},"sk":{"a":0,"k":0,"ix":4},"sa":{"a":0,"k":0,"ix":5},"nm":"Transform"}],"nm":"Group 3","np":4,"cix":2,"bm":0,"ix":3,"mn":"ADBE Vector Group","hd":false},{"ty":"gr","it":[{"ind":0,"ty":"sh","ix":1,"ks":{"a":0,"k":{"i":[[-10.109,-1.28],[-1.893,-2.039],[4.174,1.746],[1.67,0.699]],"o":[[0,0],[1.892,2.039],[-4.173,-1.746],[-1.668,-0.698]],"v":[[-4.756,-3.195],[12.973,2.436],[2.107,2.104],[2.558,0.085]],"c":true},"ix":2},"nm":"Path 1","mn":"ADBE Vector Shape - Group","hd":false},{"ty":"fl","c":{"a":0,"k":[0.972463809743,0.180861259909,0.012286408742,1],"ix":4},"o":{"a":0,"k":100,"ix":5},"r":1,"bm":0,"nm":"Fill 1","mn":"ADBE Vector Graphic - Fill","hd":false},{"ty":"tr","p":{"a":0,"k":[24.396,12.785],"ix":2},"a":{"a":0,"k":[0,0],"ix":1},"s":{"a":0,"k":[100,100],"ix":3},"r":{"a":0,"k":0,"ix":6},"o":{"a":0,"k":100,"ix":7},"sk":{"a":0,"k":0,"ix":4},"sa":{"a":0,"k":0,"ix":5},"nm":"Transform"}],"nm":"Group 4","np":4,"cix":2,"bm":0,"ix":4,"mn":"ADBE Vector Group","hd":false},{"ty":"gr","it":[{"ind":0,"ty":"sh","ix":1,"ks":{"a":0,"k":{"i":[[-0.375,1.244],[0,0],[-2.526,-0.761],[0,0],[0,0],[3.21,-3.225],[0,0],[-0.297,3.067],[0,0],[7.03,2.528],[0,0]],"o":[[0,0],[0.476,-1.58],[0,0],[9.91,2.983],[4.81,3.821],[0,0],[-5.891,8.083],[0,0],[-6.241,-3.594],[0,0],[-1.949,-0.701]],"v":[[-37.174,-23.406],[-37.137,-23.534],[-31.702,-25.017],[16.577,-10.485],[31.616,-3.073],[34.339,8.917],[30.036,17.695],[19.335,15.219],[-6.807,-8.015],[-26.808,-17.241],[-34.39,-19.967]],"c":true},"ix":2},"nm":"Path 1","mn":"ADBE Vector Shape - Group","hd":false},{"ty":"fl","c":{"a":0,"k":[0.973038377949,0.983709058575,0.172993274764,1],"ix":4},"o":{"a":0,"k":100,"ix":5},"r":1,"bm":0,"nm":"Fill 1","mn":"ADBE Vector Graphic - Fill","hd":false},{"ty":"tr","p":{"a":0,"k":[39.96,29.148],"ix":2},"a":{"a":0,"k":[0,0],"ix":1},"s":{"a":0,"k":[100,100],"ix":3},"r":{"a":0,"k":0,"ix":6},"o":{"a":0,"k":100,"ix":7},"sk":{"a":0,"k":0,"ix":4},"sa":{"a":0,"k":0,"ix":5},"nm":"Transform"}],"nm":"Group 5","np":4,"cix":2,"bm":0,"ix":5,"mn":"ADBE Vector Group","hd":false},{"ty":"gr","it":[{"ind":0,"ty":"sh","ix":1,"ks":{"a":0,"k":{"i":[[0,0],[4.344,1.176],[11.643,3.533],[1.044,-1.28],[-3.51,-2.522]],"o":[[0,0],[-3.586,-0.97],[-2.667,-0.809],[-1.258,1.542],[6.315,4.54]],"v":[[27.523,9.826],[26.372,5.673],[-22.461,-9.017],[-28.822,-8.229],[-27.206,-1.869]],"c":true},"ix":2},"nm":"Path 1","mn":"ADBE Vector Shape - Group","hd":false},{"ty":"fl","c":{"a":0,"k":[0.972463809743,0.180861259909,0.012286408742,1],"ix":4},"o":{"a":0,"k":100,"ix":5},"r":1,"bm":0,"nm":"Fill 1","mn":"ADBE Vector Graphic - Fill","hd":false},{"ty":"tr","p":{"a":0,"k":[30.966,10.076],"ix":2},"a":{"a":0,"k":[0,0],"ix":1},"s":{"a":0,"k":[100,100],"ix":3},"r":{"a":0,"k":0,"ix":6},"o":{"a":0,"k":100,"ix":7},"sk":{"a":0,"k":0,"ix":4},"sa":{"a":0,"k":0,"ix":5},"nm":"Transform"}],"nm":"Group 6","np":4,"cix":2,"bm":0,"ix":6,"mn":"ADBE Vector Group","hd":false}],"ip":47.0000019143492,"op":376.000015314794,"st":47.0000019143492,"bm":0},{"ddd":0,"ind":2,"ty":4,"nm":"Shape Layer 2","sr":1,"ks":{"o":{"a":0,"k":100,"ix":11},"r":{"a":0,"k":0,"ix":10},"p":{"a":0,"k":[190,120,0],"ix":2},"a":{"a":0,"k":[0,0,0],"ix":1},"s":{"a":0,"k":[100,100,100],"ix":6}},"ao":0,"shapes":[{"ty":"gr","it":[{"ind":0,"ty":"sh","ix":1,"ks":{"a":0,"k":{"i":[[0,0],[8.5,-4],[0,0],[0,0],[-1,9.5]],"o":[[0,0],[-8.5,4],[0,0],[0,0],[0.844,-8.018]],"v":[[97.5,70.5],[91.5,82.5],[9,112],[-75,83.5],[-81,71]],"c":false},"ix":2},"nm":"Path 1","mn":"ADBE Vector Shape - Group","hd":false},{"ty":"st","c":{"a":0,"k":[0.49253988827,0.468275182387,0.535003063725,1],"ix":3},"o":{"a":0,"k":100,"ix":4},"w":{"a":0,"k":5,"ix":5},"lc":2,"lj":1,"ml":4,"bm":0,"nm":"Stroke 1","mn":"ADBE Vector Graphic - Stroke","hd":false},{"ty":"tr","p":{"a":0,"k":[0,0],"ix":2},"a":{"a":0,"k":[0,0],"ix":1},"s":{"a":0,"k":[100,100],"ix":3},"r":{"a":0,"k":0,"ix":6},"o":{"a":0,"k":100,"ix":7},"sk":{"a":0,"k":0,"ix":4},"sa":{"a":0,"k":0,"ix":5},"nm":"Transform"}],"nm":"Shape 1","np":3,"cix":2,"bm":0,"ix":1,"mn":"ADBE Vector Group","hd":false},{"ty":"tm","s":{"a":0,"k":0,"ix":1},"e":{"a":1,"k":[{"i":{"x":[0.667],"y":[1]},"o":{"x":[0.333],"y":[0]},"t":17,"s":[0]},{"t":34.0000013848484,"s":[100]}],"ix":2},"o":{"a":0,"k":0,"ix":3},"m":1,"ix":2,"nm":"Trim Paths 1","mn":"ADBE Vector Filter - Trim","hd":false}],"ip":17.0000006924242,"op":334.000013604099,"st":5.00000020365417,"bm":0},{"ddd":0,"ind":3,"ty":4,"nm":"Shape Layer 1","sr":1,"ks":{"o":{"a":0,"k":100,"ix":11},"r":{"a":0,"k":0,"ix":10},"p":{"a":0,"k":[190,120,0],"ix":2},"a":{"a":0,"k":[0,0,0],"ix":1},"s":{"a":0,"k":[100,100,100],"ix":6}},"ao":0,"shapes":[{"ty":"gr","it":[{"ind":0,"ty":"sh","ix":1,"ks":{"a":0,"k":{"i":[[0,0],[-101,-45.5]],"o":[[0,0],[101,45.5]],"v":[[-93,-4.5],[110,-0.5]],"c":false},"ix":2},"nm":"Path 1","mn":"ADBE Vector Shape - Group","hd":false},{"ty":"st","c":{"a":0,"k":[0.494117647059,0.466666666667,0.533333333333,1],"ix":3},"o":{"a":0,"k":100,"ix":4},"w":{"a":0,"k":5,"ix":5},"lc":2,"lj":1,"ml":4,"bm":0,"nm":"Stroke 1","mn":"ADBE Vector Graphic - Stroke","hd":false},{"ty":"tr","p":{"a":0,"k":[0,0],"ix":2},"a":{"a":0,"k":[0,0],"ix":1},"s":{"a":0,"k":[100,100],"ix":3},"r":{"a":0,"k":0,"ix":6},"o":{"a":0,"k":100,"ix":7},"sk":{"a":0,"k":0,"ix":4},"sa":{"a":0,"k":0,"ix":5},"nm":"Transform"}],"nm":"Shape 1","np":3,"cix":2,"bm":0,"ix":1,"mn":"ADBE Vector Group","hd":false},{"ty":"tm","s":{"a":0,"k":0,"ix":1},"e":{"a":1,"k":[{"i":{"x":[0.667],"y":[1]},"o":{"x":[0.333],"y":[0]},"t":0,"s":[0]},{"t":17.0000006924242,"s":[100]}],"ix":2},"o":{"a":0,"k":0,"ix":3},"m":1,"ix":2,"nm":"Trim Paths 1","mn":"ADBE Vector Filter - Trim","hd":false}],"ip":0,"op":329.000013400445,"st":0,"bm":0},{"ddd":0,"ind":4,"ty":4,"nm":"Hat Outlines","sr":1,"ks":{"o":{"a":0,"k":100,"ix":11},"r":{"a":1,"k":[{"i":{"x":[0],"y":[1]},"o":{"x":[0.004],"y":[0]},"t":47,"s":[-100]},{"i":{"x":[0.667],"y":[1]},"o":{"x":[0.333],"y":[0]},"t":62,"s":[1.306]},{"t":66.0000026882351,"s":[-1.867]}],"ix":10},"p":{"a":0,"k":[72.128,144.006,0],"ix":2},"a":{"a":0,"k":[60,135,0],"ix":1},"s":{"a":1,"k":[{"i":{"x":[0,0,0.667],"y":[1,1,1]},"o":{"x":[0.004,0.004,0.333],"y":[0,0,0]},"t":47,"s":[0,0,100]},{"t":62.0000025253118,"s":[100,100,100]}],"ix":6}},"ao":0,"shapes":[{"ty":"gr","it":[{"ind":0,"ty":"sh","ix":1,"ks":{"a":0,"k":{"i":[[-5.829,22.836],[-7.299,2.938],[14.055,-8.463]],"o":[[0,0],[0,0],[0,0]],"v":[[-4.731,-16.977],[6.034,-14.972],[-3.494,16.977]],"c":true},"ix":2},"nm":"Path 1","mn":"ADBE Vector Shape - Group","hd":false},{"ty":"fl","c":{"a":0,"k":[0.099862655939,0.119835288852,0.148283820059,1],"ix":4},"o":{"a":0,"k":100,"ix":5},"r":1,"bm":0,"nm":"Fill 1","mn":"ADBE Vector Graphic - Fill","hd":false},{"ty":"tr","p":{"a":0,"k":[33.151,54.902],"ix":2},"a":{"a":0,"k":[0,0],"ix":1},"s":{"a":0,"k":[100,100],"ix":3},"r":{"a":0,"k":0,"ix":6},"o":{"a":0,"k":100,"ix":7},"sk":{"a":0,"k":0,"ix":4},"sa":{"a":0,"k":0,"ix":5},"nm":"Transform"}],"nm":"Group 1","np":4,"cix":2,"bm":0,"ix":1,"mn":"ADBE Vector Group","hd":false},{"ty":"gr","it":[{"ind":0,"ty":"sh","ix":1,"ks":{"a":0,"k":{"i":[[-0.937,-0.963],[2.059,-2.005],[0.938,0.964],[-2.059,2.004]],"o":[[0.937,0.963],[-2.059,2.003],[-0.938,-0.963],[2.059,-2.004]],"v":[[3.729,-3.63],[1.699,1.745],[-3.728,3.629],[-1.698,-1.744]],"c":true},"ix":2},"nm":"Path 1","mn":"ADBE Vector Shape - Group","hd":false},{"ty":"fl","c":{"a":0,"k":[0.366057900821,0.500315916772,0.506066715016,1],"ix":4},"o":{"a":0,"k":100,"ix":5},"r":1,"bm":0,"nm":"Fill 1","mn":"ADBE Vector Graphic - Fill","hd":false},{"ty":"tr","p":{"a":0,"k":[40.338,16.869],"ix":2},"a":{"a":0,"k":[0,0],"ix":1},"s":{"a":0,"k":[100,100],"ix":3},"r":{"a":0,"k":0,"ix":6},"o":{"a":0,"k":100,"ix":7},"sk":{"a":0,"k":0,"ix":4},"sa":{"a":0,"k":0,"ix":5},"nm":"Transform"}],"nm":"Group 2","np":4,"cix":2,"bm":0,"ix":2,"mn":"ADBE Vector Group","hd":false},{"ty":"gr","it":[{"ind":0,"ty":"sh","ix":1,"ks":{"a":0,"k":{"i":[[-22.63,-23.247],[0,0],[0,0]],"o":[[0,0],[-24.635,-26.516],[-21.186,20.625]],"v":[[2.457,39.719],[21.343,21.334],[-0.157,-39.719]],"c":true},"ix":2},"nm":"Path 1","mn":"ADBE Vector Shape - Group","hd":false},{"ty":"fl","c":{"a":0,"k":[0.249367927102,0.299257435518,0.370306366565,1],"ix":4},"o":{"a":0,"k":100,"ix":5},"r":1,"bm":0,"nm":"Fill 1","mn":"ADBE Vector Graphic - Fill","hd":false},{"ty":"tr","p":{"a":0,"k":[40.434,58.12],"ix":2},"a":{"a":0,"k":[0,0],"ix":1},"s":{"a":0,"k":[100,100],"ix":3},"r":{"a":0,"k":0,"ix":6},"o":{"a":0,"k":100,"ix":7},"sk":{"a":0,"k":0,"ix":4},"sa":{"a":0,"k":0,"ix":5},"nm":"Transform"}],"nm":"Group 3","np":4,"cix":2,"bm":0,"ix":3,"mn":"ADBE Vector Group","hd":false},{"ty":"gr","it":[{"ind":0,"ty":"sh","ix":1,"ks":{"a":0,"k":{"i":[[0,0],[0,0],[0,0],[15.936,-15.514],[-22.631,-23.247],[0,0],[3.31,2.301]],"o":[[0,0],[0,0],[-20.57,-9.536],[-21.187,20.625],[0,0],[-2.935,-3.016],[0,0]],"v":[[28.296,-21.634],[21.035,-29.093],[31.477,-39.259],[-29.075,-30.643],[-26.462,48.795],[50.262,-25.896],[40.861,-33.866]],"c":true},"ix":2},"nm":"Path 1","mn":"ADBE Vector Shape - Group","hd":false},{"ty":"fl","c":{"a":0,"k":[0.362234856101,0.434672157437,0.537864236271,1],"ix":4},"o":{"a":0,"k":100,"ix":5},"r":1,"bm":0,"nm":"Fill 1","mn":"ADBE Vector Graphic - Fill","hd":false},{"ty":"tr","p":{"a":0,"k":[69.353,49.045],"ix":2},"a":{"a":0,"k":[0,0],"ix":1},"s":{"a":0,"k":[100,100],"ix":3},"r":{"a":0,"k":0,"ix":6},"o":{"a":0,"k":100,"ix":7},"sk":{"a":0,"k":0,"ix":4},"sa":{"a":0,"k":0,"ix":5},"nm":"Transform"}],"nm":"Group 4","np":4,"cix":2,"bm":0,"ix":4,"mn":"ADBE Vector Group","hd":false},{"ty":"gr","it":[{"ind":0,"ty":"sh","ix":1,"ks":{"a":0,"k":{"i":[[1.447,-1.408],[0,0],[1.408,1.447],[-1.447,1.409],[0,0],[-1.408,-1.447]],"o":[[0,0],[-1.447,1.409],[-1.409,-1.447],[0,0],[1.447,-1.408],[1.409,1.447]],"v":[[26.926,-21.111],[-21.826,26.348],[-26.995,26.279],[-26.926,21.109],[21.826,-26.35],[26.995,-26.281]],"c":true},"ix":2},"nm":"Path 1","mn":"ADBE Vector Shape - Group","hd":false},{"ty":"fl","c":{"a":0,"k":[0.095863357245,0.11503570407,0.1423449348,1],"ix":4},"o":{"a":0,"k":100,"ix":5},"r":1,"bm":0,"nm":"Fill 1","mn":"ADBE Vector Graphic - Fill","hd":false},{"ty":"tr","p":{"a":0,"k":[28.654,106.596],"ix":2},"a":{"a":0,"k":[0,0],"ix":1},"s":{"a":0,"k":[100,100],"ix":3},"r":{"a":0,"k":0,"ix":6},"o":{"a":0,"k":100,"ix":7},"sk":{"a":0,"k":0,"ix":4},"sa":{"a":0,"k":0,"ix":5},"nm":"Transform"}],"nm":"Group 5","np":4,"cix":2,"bm":0,"ix":5,"mn":"ADBE Vector Group","hd":false}],"ip":47.0000019143492,"op":376.000015314794,"st":47.0000019143492,"bm":0},{"ddd":0,"ind":5,"ty":4,"nm":"Shape Layer 3","td":1,"sr":1,"ks":{"o":{"a":0,"k":100,"ix":11},"r":{"a":0,"k":0,"ix":10},"p":{"a":0,"k":[190,120,0],"ix":2},"a":{"a":0,"k":[0,0,0],"ix":1},"s":{"a":0,"k":[100,100,100],"ix":6}},"ao":0,"shapes":[{"ty":"gr","it":[{"ind":0,"ty":"sh","ix":1,"ks":{"a":0,"k":{"i":[[0,0],[0,0],[0,0],[0,0],[-49,-9]],"o":[[0,0],[0,0],[0,0],[0,0],[49,9]],"v":[[59.5,-129.5],[-153.5,-126],[-156.5,-61],[-95,-5],[21,-20.5]],"c":true},"ix":2},"nm":"Path 1","mn":"ADBE Vector Shape - Group","hd":false},{"ty":"fl","c":{"a":0,"k":[0.657447665345,0.892769607843,0.256985832663,1],"ix":4},"o":{"a":0,"k":100,"ix":5},"r":1,"bm":0,"nm":"Fill 1","mn":"ADBE Vector Graphic - Fill","hd":false},{"ty":"tr","p":{"a":0,"k":[0,0],"ix":2},"a":{"a":0,"k":[0,0],"ix":1},"s":{"a":0,"k":[100,100],"ix":3},"r":{"a":0,"k":0,"ix":6},"o":{"a":0,"k":100,"ix":7},"sk":{"a":0,"k":0,"ix":4},"sa":{"a":0,"k":0,"ix":5},"nm":"Transform"}],"nm":"Shape 1","np":3,"cix":2,"bm":0,"ix":1,"mn":"ADBE Vector Group","hd":false}],"ip":0,"op":329.000013400445,"st":0,"bm":0},{"ddd":0,"ind":6,"ty":4,"nm":"Football Outlines","tt":1,"sr":1,"ks":{"o":{"a":0,"k":100,"ix":11},"r":{"a":1,"k":[{"i":{"x":[0],"y":[1]},"o":{"x":[0.006],"y":[0]},"t":34,"s":[-100]},{"i":{"x":[0.667],"y":[1]},"o":{"x":[0.333],"y":[0]},"t":49,"s":[12.127]},{"t":53.0000021587343,"s":[0]}],"ix":10},"p":{"a":0,"k":[143.529,99.555,0],"ix":2},"a":{"a":0,"k":[60.899,81.05,0],"ix":1},"s":{"a":1,"k":[{"i":{"x":[0,0,0.667],"y":[1,1,1]},"o":{"x":[0.006,0.006,0.333],"y":[0,0,0]},"t":34,"s":[0,0,100]},{"t":49.0000019958109,"s":[100,100,100]}],"ix":6}},"ao":0,"shapes":[{"ty":"gr","it":[{"ind":0,"ty":"sh","ix":1,"ks":{"a":0,"k":{"i":[[0,0],[-1.556,2.218],[0,0],[2.882,0.732]],"o":[[2.043,-2.208],[0,0],[-2.435,-1.024],[0,0]],"v":[[4.11,24.523],[9.494,17.852],[-1.52,-21.857],[-9.494,-24.523]],"c":true},"ix":2},"nm":"Path 1","mn":"ADBE Vector Shape - Group","hd":false},{"ty":"fl","c":{"a":0,"k":[0.972481940774,0.652003568761,0.051666663675,1],"ix":4},"o":{"a":0,"k":100,"ix":5},"r":1,"bm":0,"nm":"Fill 1","mn":"ADBE Vector Graphic - Fill","hd":false},{"ty":"tr","p":{"a":0,"k":[94.394,36.268],"ix":2},"a":{"a":0,"k":[0,0],"ix":1},"s":{"a":0,"k":[100,100],"ix":3},"r":{"a":0,"k":0,"ix":6},"o":{"a":0,"k":100,"ix":7},"sk":{"a":0,"k":0,"ix":4},"sa":{"a":0,"k":0,"ix":5},"nm":"Transform"}],"nm":"Group 1","np":4,"cix":2,"bm":0,"ix":1,"mn":"ADBE Vector Group","hd":false},{"ty":"gr","it":[{"ind":0,"ty":"sh","ix":1,"ks":{"a":0,"k":{"i":[[0,0],[-2.834,-0.687],[0,0],[1.604,-2.178]],"o":[[2.452,0.964],[0,0],[-2.023,2.147],[0,0]],"v":[[1.667,22.309],[9.596,24.814],[-4.169,-24.814],[-9.596,-18.296]],"c":true},"ix":2},"nm":"Path 1","mn":"ADBE Vector Shape - Group","hd":false},{"ty":"fl","c":{"a":0,"k":[0.972481940774,0.652003568761,0.051666663675,1],"ix":4},"o":{"a":0,"k":100,"ix":5},"r":1,"bm":0,"nm":"Fill 1","mn":"ADBE Vector Graphic - Fill","hd":false},{"ty":"tr","p":{"a":0,"k":[21.666,56.104],"ix":2},"a":{"a":0,"k":[0,0],"ix":1},"s":{"a":0,"k":[100,100],"ix":3},"r":{"a":0,"k":0,"ix":6},"o":{"a":0,"k":100,"ix":7},"sk":{"a":0,"k":0,"ix":4},"sa":{"a":0,"k":0,"ix":5},"nm":"Transform"}],"nm":"Group 2","np":4,"cix":2,"bm":0,"ix":2,"mn":"ADBE Vector Group","hd":false},{"ty":"gr","it":[{"ind":0,"ty":"sh","ix":1,"ks":{"a":0,"k":{"i":[[0.822,-0.229],[0.228,0.822],[0,0],[-0.823,0.228],[-0.228,-0.822],[0,0]],"o":[[-0.823,0.228],[0,0],[-0.228,-0.822],[0.822,-0.228],[0,0],[0.228,0.822]],"v":[[2.044,7.368],[0.142,6.292],[-3.12,-5.466],[-2.043,-7.368],[-0.142,-6.292],[3.12,5.466]],"c":true},"ix":2},"nm":"Path 1","mn":"ADBE Vector Shape - Group","hd":false},{"ty":"fl","c":{"a":0,"k":[0.97633152382,0.989677518957,0.451962011001,1],"ix":4},"o":{"a":0,"k":100,"ix":5},"r":1,"bm":0,"nm":"Fill 1","mn":"ADBE Vector Graphic - Fill","hd":false},{"ty":"tr","p":{"a":0,"k":[67.336,42.995],"ix":2},"a":{"a":0,"k":[0,0],"ix":1},"s":{"a":0,"k":[100,100],"ix":3},"r":{"a":0,"k":0,"ix":6},"o":{"a":0,"k":100,"ix":7},"sk":{"a":0,"k":0,"ix":4},"sa":{"a":0,"k":0,"ix":5},"nm":"Transform"}],"nm":"Group 3","np":4,"cix":2,"bm":0,"ix":3,"mn":"ADBE Vector Group","hd":false},{"ty":"gr","it":[{"ind":0,"ty":"sh","ix":1,"ks":{"a":0,"k":{"i":[[0.823,-0.228],[0.228,0.822],[0,0],[-0.822,0.228],[-0.228,-0.822],[0,0]],"o":[[-0.822,0.228],[0,0],[-0.228,-0.822],[0.822,-0.228],[0,0],[0.228,0.822]],"v":[[2.044,7.368],[0.142,6.292],[-3.12,-5.466],[-2.044,-7.368],[-0.142,-6.292],[3.12,5.466]],"c":true},"ix":2},"nm":"Path 1","mn":"ADBE Vector Shape - Group","hd":false},{"ty":"fl","c":{"a":0,"k":[0.97633152382,0.989677518957,0.451962011001,1],"ix":4},"o":{"a":0,"k":100,"ix":5},"r":1,"bm":0,"nm":"Fill 1","mn":"ADBE Vector Graphic - Fill","hd":false},{"ty":"tr","p":{"a":0,"k":[60.662,44.846],"ix":2},"a":{"a":0,"k":[0,0],"ix":1},"s":{"a":0,"k":[100,100],"ix":3},"r":{"a":0,"k":0,"ix":6},"o":{"a":0,"k":100,"ix":7},"sk":{"a":0,"k":0,"ix":4},"sa":{"a":0,"k":0,"ix":5},"nm":"Transform"}],"nm":"Group 4","np":4,"cix":2,"bm":0,"ix":4,"mn":"ADBE Vector Group","hd":false},{"ty":"gr","it":[{"ind":0,"ty":"sh","ix":1,"ks":{"a":0,"k":{"i":[[0.822,-0.228],[0.228,0.822],[0,0],[-0.822,0.228],[-0.228,-0.822],[0,0]],"o":[[-0.822,0.228],[0,0],[-0.228,-0.822],[0.822,-0.228],[0,0],[0.228,0.822]],"v":[[2.044,7.368],[0.142,6.292],[-3.12,-5.466],[-2.044,-7.368],[-0.142,-6.292],[3.12,5.466]],"c":true},"ix":2},"nm":"Path 1","mn":"ADBE Vector Shape - Group","hd":false},{"ty":"fl","c":{"a":0,"k":[0.97633152382,0.989677518957,0.451962011001,1],"ix":4},"o":{"a":0,"k":100,"ix":5},"r":1,"bm":0,"nm":"Fill 1","mn":"ADBE Vector Graphic - Fill","hd":false},{"ty":"tr","p":{"a":0,"k":[53.988,46.697],"ix":2},"a":{"a":0,"k":[0,0],"ix":1},"s":{"a":0,"k":[100,100],"ix":3},"r":{"a":0,"k":0,"ix":6},"o":{"a":0,"k":100,"ix":7},"sk":{"a":0,"k":0,"ix":4},"sa":{"a":0,"k":0,"ix":5},"nm":"Transform"}],"nm":"Group 5","np":4,"cix":2,"bm":0,"ix":5,"mn":"ADBE Vector Group","hd":false},{"ty":"gr","it":[{"ind":0,"ty":"sh","ix":1,"ks":{"a":0,"k":{"i":[[0.822,-0.228],[0.228,0.822],[0,0],[-0.823,0.228],[-0.228,-0.822],[0,0]],"o":[[-0.822,0.228],[0,0],[-0.228,-0.822],[0.822,-0.228],[0,0],[0.228,0.822]],"v":[[2.044,7.368],[0.142,6.292],[-3.119,-5.466],[-2.044,-7.368],[-0.142,-6.292],[3.12,5.466]],"c":true},"ix":2},"nm":"Path 1","mn":"ADBE Vector Shape - Group","hd":false},{"ty":"fl","c":{"a":0,"k":[0.97633152382,0.989677518957,0.451962011001,1],"ix":4},"o":{"a":0,"k":100,"ix":5},"r":1,"bm":0,"nm":"Fill 1","mn":"ADBE Vector Graphic - Fill","hd":false},{"ty":"tr","p":{"a":0,"k":[47.314,48.548],"ix":2},"a":{"a":0,"k":[0,0],"ix":1},"s":{"a":0,"k":[100,100],"ix":3},"r":{"a":0,"k":0,"ix":6},"o":{"a":0,"k":100,"ix":7},"sk":{"a":0,"k":0,"ix":4},"sa":{"a":0,"k":0,"ix":5},"nm":"Transform"}],"nm":"Group 6","np":4,"cix":2,"bm":0,"ix":6,"mn":"ADBE Vector Group","hd":false},{"ty":"gr","it":[{"ind":0,"ty":"sh","ix":1,"ks":{"a":0,"k":{"i":[[0.822,-0.229],[0,0],[0.229,0.823],[-0.822,0.228],[0,0],[-0.228,-0.823]],"o":[[0,0],[-0.823,0.228],[-0.228,-0.822],[0,0],[0.822,-0.228],[0.228,0.822]],"v":[[20.248,-4.012],[-19.42,6.991],[-21.323,5.915],[-20.247,4.012],[19.422,-6.991],[21.324,-5.914]],"c":true},"ix":2},"nm":"Path 1","mn":"ADBE Vector Shape - Group","hd":false},{"ty":"fl","c":{"a":0,"k":[0.97633152382,0.989677518957,0.451962011001,1],"ix":4},"o":{"a":0,"k":100,"ix":5},"r":1,"bm":0,"nm":"Fill 1","mn":"ADBE Vector Graphic - Fill","hd":false},{"ty":"tr","p":{"a":0,"k":[57.802,45.949],"ix":2},"a":{"a":0,"k":[0,0],"ix":1},"s":{"a":0,"k":[100,100],"ix":3},"r":{"a":0,"k":0,"ix":6},"o":{"a":0,"k":100,"ix":7},"sk":{"a":0,"k":0,"ix":4},"sa":{"a":0,"k":0,"ix":5},"nm":"Transform"}],"nm":"Group 7","np":4,"cix":2,"bm":0,"ix":7,"mn":"ADBE Vector Group","hd":false},{"ty":"gr","it":[{"ind":0,"ty":"sh","ix":1,"ks":{"a":0,"k":{"i":[[0,0],[-43.488,12.062],[0,0],[0.064,0.092],[0,0]],"o":[[0,0],[42.131,-11.686],[0,0],[0,0],[-0.029,0.118]],"v":[[-56.918,1.03],[9.26,18.627],[56.918,-30.545],[56.819,-30.689],[-56.874,0.844]],"c":true},"ix":2},"nm":"Path 1","mn":"ADBE Vector Shape - Group","hd":false},{"ty":"fl","c":{"a":0,"k":[0.763115617341,0.322516198252,0.020241236219,1],"ix":4},"o":{"a":0,"k":100,"ix":5},"r":1,"bm":0,"nm":"Fill 1","mn":"ADBE Vector Graphic - Fill","hd":false},{"ty":"tr","p":{"a":0,"k":[57.168,61.161],"ix":2},"a":{"a":0,"k":[0,0],"ix":1},"s":{"a":0,"k":[100,100],"ix":3},"r":{"a":0,"k":0,"ix":6},"o":{"a":0,"k":100,"ix":7},"sk":{"a":0,"k":0,"ix":4},"sa":{"a":0,"k":0,"ix":5},"nm":"Transform"}],"nm":"Group 8","np":4,"cix":2,"bm":0,"ix":8,"mn":"ADBE Vector Group","hd":false},{"ty":"gr","it":[{"ind":0,"ty":"sh","ix":1,"ks":{"a":0,"k":{"i":[[0,0],[42.132,-11.686],[0,0],[-39.124,10.852]],"o":[[0,0],[-43.487,12.062],[0,0],[46.041,-12.77]],"v":[[56.918,-15.433],[9.259,33.738],[-56.918,16.142],[-9.26,-33.03]],"c":true},"ix":2},"nm":"Path 1","mn":"ADBE Vector Shape - Group","hd":false},{"ty":"fl","c":{"a":0,"k":[0.972714891621,0.412282278024,0.015603322609,1],"ix":4},"o":{"a":0,"k":100,"ix":5},"r":1,"bm":0,"nm":"Fill 1","mn":"ADBE Vector Graphic - Fill","hd":false},{"ty":"tr","p":{"a":0,"k":[57.168,46.05],"ix":2},"a":{"a":0,"k":[0,0],"ix":1},"s":{"a":0,"k":[100,100],"ix":3},"r":{"a":0,"k":0,"ix":6},"o":{"a":0,"k":100,"ix":7},"sk":{"a":0,"k":0,"ix":4},"sa":{"a":0,"k":0,"ix":5},"nm":"Transform"}],"nm":"Group 9","np":4,"cix":2,"bm":0,"ix":9,"mn":"ADBE Vector Group","hd":false}],"ip":34.0000013848484,"op":363.000014785293,"st":34.0000013848484,"bm":0},{"ddd":0,"ind":7,"ty":4,"nm":"Shape Layer 4","td":1,"sr":1,"ks":{"o":{"a":0,"k":100,"ix":11},"r":{"a":0,"k":0,"ix":10},"p":{"a":0,"k":[190,120,0],"ix":2},"a":{"a":0,"k":[0,0,0],"ix":1},"s":{"a":0,"k":[100,100,100],"ix":6}},"ao":0,"shapes":[{"ty":"gr","it":[{"ind":0,"ty":"sh","ix":1,"ks":{"a":0,"k":{"i":[[0,0],[0,0],[0,0],[-39,-33.5],[0,0]],"o":[[0,0],[0,0],[0,0],[39,33.5],[0,0]],"v":[[-19.5,-154],[-51,-64],[-21,-20.5],[110.5,3.5],[147.5,-133]],"c":true},"ix":2},"nm":"Path 1","mn":"ADBE Vector Shape - Group","hd":false},{"ty":"fl","c":{"a":0,"k":[0.657447665345,0.892769607843,0.256985832663,1],"ix":4},"o":{"a":0,"k":100,"ix":5},"r":1,"bm":0,"nm":"Fill 1","mn":"ADBE Vector Graphic - Fill","hd":false},{"ty":"tr","p":{"a":0,"k":[0,0],"ix":2},"a":{"a":0,"k":[0,0],"ix":1},"s":{"a":0,"k":[100,100],"ix":3},"r":{"a":0,"k":0,"ix":6},"o":{"a":0,"k":100,"ix":7},"sk":{"a":0,"k":0,"ix":4},"sa":{"a":0,"k":0,"ix":5},"nm":"Transform"}],"nm":"Shape 1","np":3,"cix":2,"bm":0,"ix":1,"mn":"ADBE Vector Group","hd":false}],"ip":0,"op":329.000013400445,"st":0,"bm":0},{"ddd":0,"ind":8,"ty":4,"nm":"Mug Outlines","tt":1,"sr":1,"ks":{"o":{"a":0,"k":100,"ix":11},"r":{"a":1,"k":[{"i":{"x":[0.667],"y":[1]},"o":{"x":[0.333],"y":[0]},"t":38,"s":[100]},{"t":53.0000021587343,"s":[0]}],"ix":10},"p":{"a":0,"k":[197.63,98.974,0],"ix":2},"a":{"a":0,"k":[-0.788,93,0],"ix":1},"s":{"a":1,"k":[{"i":{"x":[0.667,0.667,0.667],"y":[1,1,1]},"o":{"x":[0.333,0.333,0.333],"y":[0,0,0]},"t":38,"s":[0,0,100]},{"t":53.0000021587343,"s":[100,100,100]}],"ix":6}},"ao":0,"shapes":[{"ty":"gr","it":[{"ind":0,"ty":"sh","ix":1,"ks":{"a":0,"k":{"i":[[1.852,0.136],[0,0],[-0.136,1.851],[0,0],[-1.853,-0.136],[0.137,-1.851],[0,0]],"o":[[0,0],[-1.852,-0.136],[0,0],[0.136,-1.851],[1.851,0.136],[0,0],[-0.136,1.851]],"v":[[-1.918,27.033],[-1.918,27.033],[-5.024,23.434],[-1.554,-23.8],[2.046,-26.906],[5.151,-23.307],[1.681,23.927]],"c":true},"ix":2},"nm":"Path 1","mn":"ADBE Vector Shape - Group","hd":false},{"ty":"fl","c":{"a":0,"k":[0.16471752092,0.245511387844,0.393210078221,1],"ix":4},"o":{"a":0,"k":100,"ix":5},"r":1,"bm":0,"nm":"Fill 1","mn":"ADBE Vector Graphic - Fill","hd":false},{"ty":"tr","p":{"a":0,"k":[44.367,52.191],"ix":2},"a":{"a":0,"k":[0,0],"ix":1},"s":{"a":0,"k":[100,100],"ix":3},"r":{"a":0,"k":0,"ix":6},"o":{"a":0,"k":100,"ix":7},"sk":{"a":0,"k":0,"ix":4},"sa":{"a":0,"k":0,"ix":5},"nm":"Transform"}],"nm":"Group 1","np":4,"cix":2,"bm":3,"ix":1,"mn":"ADBE Vector Group","hd":false},{"ty":"gr","it":[{"ind":0,"ty":"sh","ix":1,"ks":{"a":0,"k":{"i":[[1.852,0.136],[0,0],[-0.136,1.851],[0,0],[-1.852,-0.136],[0.136,-1.851],[0,0]],"o":[[0,0],[-1.852,-0.136],[0,0],[0.137,-1.851],[1.851,0.136],[0,0],[-0.137,1.851]],"v":[[-1.982,26.969],[-1.982,26.969],[-5.088,23.37],[-1.618,-23.863],[1.982,-26.969],[5.088,-23.37],[1.618,23.864]],"c":true},"ix":2},"nm":"Path 1","mn":"ADBE Vector Shape - Group","hd":false},{"ty":"fl","c":{"a":0,"k":[0.16471752092,0.245511387844,0.393210078221,1],"ix":4},"o":{"a":0,"k":100,"ix":5},"r":1,"bm":0,"nm":"Fill 1","mn":"ADBE Vector Graphic - Fill","hd":false},{"ty":"tr","p":{"a":0,"k":[31.448,51.301],"ix":2},"a":{"a":0,"k":[0,0],"ix":1},"s":{"a":0,"k":[100,100],"ix":3},"r":{"a":0,"k":0,"ix":6},"o":{"a":0,"k":100,"ix":7},"sk":{"a":0,"k":0,"ix":4},"sa":{"a":0,"k":0,"ix":5},"nm":"Transform"}],"nm":"Group 2","np":4,"cix":2,"bm":3,"ix":2,"mn":"ADBE Vector Group","hd":false},{"ty":"gr","it":[{"ind":0,"ty":"sh","ix":1,"ks":{"a":0,"k":{"i":[[1.852,0.136],[0,0],[-0.136,1.851],[0,0],[-1.852,-0.137],[0.136,-1.852],[0,0]],"o":[[0,0],[-1.852,-0.136],[0,0],[0.136,-1.851],[1.851,0.135],[0,0],[-0.136,1.852]],"v":[[-2.045,26.906],[-2.045,26.906],[-5.151,23.307],[-1.681,-23.927],[1.919,-27.032],[5.025,-23.433],[1.554,23.8]],"c":true},"ix":2},"nm":"Path 1","mn":"ADBE Vector Shape - Group","hd":false},{"ty":"fl","c":{"a":0,"k":[0.16471752092,0.245511387844,0.393210078221,1],"ix":4},"o":{"a":0,"k":100,"ix":5},"r":1,"bm":0,"nm":"Fill 1","mn":"ADBE Vector Graphic - Fill","hd":false},{"ty":"tr","p":{"a":0,"k":[17.93,50.366],"ix":2},"a":{"a":0,"k":[0,0],"ix":1},"s":{"a":0,"k":[100,100],"ix":3},"r":{"a":0,"k":0,"ix":6},"o":{"a":0,"k":100,"ix":7},"sk":{"a":0,"k":0,"ix":4},"sa":{"a":0,"k":0,"ix":5},"nm":"Transform"}],"nm":"Group 3","np":4,"cix":2,"bm":3,"ix":3,"mn":"ADBE Vector Group","hd":false},{"ty":"gr","it":[{"ind":0,"ty":"sh","ix":1,"ks":{"a":0,"k":{"i":[[0.067,-0.928],[0.928,0.069],[-0.069,0.928],[-0.927,-0.068]],"o":[[-0.068,0.928],[-0.927,-0.068],[0.068,-0.927],[0.928,0.068]],"v":[[1.681,0.123],[-0.123,1.679],[-1.678,-0.124],[0.124,-1.68]],"c":true},"ix":2},"nm":"Path 1","mn":"ADBE Vector Shape - Group","hd":false},{"ty":"fl","c":{"a":0,"k":[0.900282257678,0.867402200138,0.019998101627,1],"ix":4},"o":{"a":0,"k":100,"ix":5},"r":1,"bm":0,"nm":"Fill 1","mn":"ADBE Vector Graphic - Fill","hd":false},{"ty":"tr","p":{"a":0,"k":[27.569,79.045],"ix":2},"a":{"a":0,"k":[0,0],"ix":1},"s":{"a":0,"k":[100,100],"ix":3},"r":{"a":0,"k":0,"ix":6},"o":{"a":0,"k":100,"ix":7},"sk":{"a":0,"k":0,"ix":4},"sa":{"a":0,"k":0,"ix":5},"nm":"Transform"}],"nm":"Group 4","np":4,"cix":2,"bm":0,"ix":4,"mn":"ADBE Vector Group","hd":false},{"ty":"gr","it":[{"ind":0,"ty":"sh","ix":1,"ks":{"a":0,"k":{"i":[[0.061,-0.825],[0.826,0.061],[-0.061,0.824],[-0.824,-0.061]],"o":[[-0.061,0.825],[-0.824,-0.06],[0.06,-0.825],[0.824,0.061]],"v":[[1.493,0.11],[-0.111,1.493],[-1.493,-0.109],[0.109,-1.493]],"c":true},"ix":2},"nm":"Path 1","mn":"ADBE Vector Shape - Group","hd":false},{"ty":"fl","c":{"a":0,"k":[0.900282257678,0.867402200138,0.019998101627,1],"ix":4},"o":{"a":0,"k":100,"ix":5},"r":1,"bm":0,"nm":"Fill 1","mn":"ADBE Vector Graphic - Fill","hd":false},{"ty":"tr","p":{"a":0,"k":[18.925,35.815],"ix":2},"a":{"a":0,"k":[0,0],"ix":1},"s":{"a":0,"k":[100,100],"ix":3},"r":{"a":0,"k":0,"ix":6},"o":{"a":0,"k":100,"ix":7},"sk":{"a":0,"k":0,"ix":4},"sa":{"a":0,"k":0,"ix":5},"nm":"Transform"}],"nm":"Group 5","np":4,"cix":2,"bm":0,"ix":5,"mn":"ADBE Vector Group","hd":false},{"ty":"gr","it":[{"ind":0,"ty":"sh","ix":1,"ks":{"a":0,"k":{"i":[[0.053,-0.721],[0.721,0.054],[-0.054,0.722],[-0.722,-0.053]],"o":[[-0.053,0.722],[-0.722,-0.052],[0.052,-0.721],[0.722,0.053]],"v":[[1.307,0.095],[-0.096,1.305],[-1.306,-0.096],[0.096,-1.307]],"c":true},"ix":2},"nm":"Path 1","mn":"ADBE Vector Shape - Group","hd":false},{"ty":"fl","c":{"a":0,"k":[0.900282257678,0.867402200138,0.019998101627,1],"ix":4},"o":{"a":0,"k":100,"ix":5},"r":1,"bm":0,"nm":"Fill 1","mn":"ADBE Vector Graphic - Fill","hd":false},{"ty":"tr","p":{"a":0,"k":[30.668,36.866],"ix":2},"a":{"a":0,"k":[0,0],"ix":1},"s":{"a":0,"k":[100,100],"ix":3},"r":{"a":0,"k":0,"ix":6},"o":{"a":0,"k":100,"ix":7},"sk":{"a":0,"k":0,"ix":4},"sa":{"a":0,"k":0,"ix":5},"nm":"Transform"}],"nm":"Group 6","np":4,"cix":2,"bm":0,"ix":6,"mn":"ADBE Vector Group","hd":false},{"ty":"gr","it":[{"ind":0,"ty":"sh","ix":1,"ks":{"a":0,"k":{"i":[[0.067,-0.928],[0.928,0.069],[-0.069,0.928],[-0.927,-0.068]],"o":[[-0.068,0.928],[-0.927,-0.068],[0.068,-0.927],[0.928,0.068]],"v":[[1.681,0.123],[-0.123,1.679],[-1.678,-0.124],[0.124,-1.68]],"c":true},"ix":2},"nm":"Path 1","mn":"ADBE Vector Shape - Group","hd":false},{"ty":"fl","c":{"a":0,"k":[0.900282257678,0.867402200138,0.019998101627,1],"ix":4},"o":{"a":0,"k":100,"ix":5},"r":1,"bm":0,"nm":"Fill 1","mn":"ADBE Vector Graphic - Fill","hd":false},{"ty":"tr","p":{"a":0,"k":[45.424,70.975],"ix":2},"a":{"a":0,"k":[0,0],"ix":1},"s":{"a":0,"k":[100,100],"ix":3},"r":{"a":0,"k":0,"ix":6},"o":{"a":0,"k":100,"ix":7},"sk":{"a":0,"k":0,"ix":4},"sa":{"a":0,"k":0,"ix":5},"nm":"Transform"}],"nm":"Group 7","np":4,"cix":2,"bm":0,"ix":7,"mn":"ADBE Vector Group","hd":false},{"ty":"gr","it":[{"ind":0,"ty":"sh","ix":1,"ks":{"a":0,"k":{"i":[[0.053,-0.722],[0.72,0.054],[-0.053,0.722],[-0.722,-0.054]],"o":[[-0.054,0.722],[-0.722,-0.053],[0.052,-0.722],[0.722,0.053]],"v":[[1.307,0.096],[-0.096,1.306],[-1.307,-0.096],[0.095,-1.306]],"c":true},"ix":2},"nm":"Path 1","mn":"ADBE Vector Shape - Group","hd":false},{"ty":"fl","c":{"a":0,"k":[0.900282257678,0.867402200138,0.019998101627,1],"ix":4},"o":{"a":0,"k":100,"ix":5},"r":1,"bm":0,"nm":"Fill 1","mn":"ADBE Vector Graphic - Fill","hd":false},{"ty":"tr","p":{"a":0,"k":[46.763,42.552],"ix":2},"a":{"a":0,"k":[0,0],"ix":1},"s":{"a":0,"k":[100,100],"ix":3},"r":{"a":0,"k":0,"ix":6},"o":{"a":0,"k":100,"ix":7},"sk":{"a":0,"k":0,"ix":4},"sa":{"a":0,"k":0,"ix":5},"nm":"Transform"}],"nm":"Group 8","np":4,"cix":2,"bm":0,"ix":8,"mn":"ADBE Vector Group","hd":false},{"ty":"gr","it":[{"ind":0,"ty":"sh","ix":1,"ks":{"a":0,"k":{"i":[[0.068,-0.928],[0.927,0.069],[-0.069,0.928],[-0.927,-0.068]],"o":[[-0.068,0.928],[-0.927,-0.068],[0.068,-0.928],[0.928,0.068]],"v":[[1.68,0.123],[-0.123,1.679],[-1.679,-0.124],[0.123,-1.68]],"c":true},"ix":2},"nm":"Path 1","mn":"ADBE Vector Shape - Group","hd":false},{"ty":"fl","c":{"a":0,"k":[0.900282257678,0.867402200138,0.019998101627,1],"ix":4},"o":{"a":0,"k":100,"ix":5},"r":1,"bm":0,"nm":"Fill 1","mn":"ADBE Vector Graphic - Fill","hd":false},{"ty":"tr","p":{"a":0,"k":[21.881,44.102],"ix":2},"a":{"a":0,"k":[0,0],"ix":1},"s":{"a":0,"k":[100,100],"ix":3},"r":{"a":0,"k":0,"ix":6},"o":{"a":0,"k":100,"ix":7},"sk":{"a":0,"k":0,"ix":4},"sa":{"a":0,"k":0,"ix":5},"nm":"Transform"}],"nm":"Group 9","np":4,"cix":2,"bm":0,"ix":9,"mn":"ADBE Vector Group","hd":false},{"ty":"gr","it":[{"ind":0,"ty":"sh","ix":1,"ks":{"a":0,"k":{"i":[[0.076,-1.031],[1.031,0.076],[-0.077,1.03],[-1.031,-0.076]],"o":[[-0.076,1.031],[-1.03,-0.076],[0.075,-1.031],[1.031,0.075]],"v":[[1.867,0.137],[-0.138,1.866],[-1.866,-0.137],[0.138,-1.866]],"c":true},"ix":2},"nm":"Path 1","mn":"ADBE Vector Shape - Group","hd":false},{"ty":"fl","c":{"a":0,"k":[0.900282257678,0.867402200138,0.019998101627,1],"ix":4},"o":{"a":0,"k":100,"ix":5},"r":1,"bm":0,"nm":"Fill 1","mn":"ADBE Vector Graphic - Fill","hd":false},{"ty":"tr","p":{"a":0,"k":[37.072,54.412],"ix":2},"a":{"a":0,"k":[0,0],"ix":1},"s":{"a":0,"k":[100,100],"ix":3},"r":{"a":0,"k":0,"ix":6},"o":{"a":0,"k":100,"ix":7},"sk":{"a":0,"k":0,"ix":4},"sa":{"a":0,"k":0,"ix":5},"nm":"Transform"}],"nm":"Group 10","np":4,"cix":2,"bm":0,"ix":10,"mn":"ADBE Vector Group","hd":false},{"ty":"gr","it":[{"ind":0,"ty":"sh","ix":1,"ks":{"a":0,"k":{"i":[[0.075,-1.031],[1.031,0.076],[-0.077,1.03],[-1.031,-0.076]],"o":[[-0.076,1.031],[-1.03,-0.076],[0.075,-1.031],[1.031,0.075]],"v":[[1.867,0.137],[-0.137,1.866],[-1.865,-0.137],[0.138,-1.866]],"c":true},"ix":2},"nm":"Path 1","mn":"ADBE Vector Shape - Group","hd":false},{"ty":"fl","c":{"a":0,"k":[0.900282257678,0.867402200138,0.019998101627,1],"ix":4},"o":{"a":0,"k":100,"ix":5},"r":1,"bm":0,"nm":"Fill 1","mn":"ADBE Vector Graphic - Fill","hd":false},{"ty":"tr","p":{"a":0,"k":[17.894,70.265],"ix":2},"a":{"a":0,"k":[0,0],"ix":1},"s":{"a":0,"k":[100,100],"ix":3},"r":{"a":0,"k":0,"ix":6},"o":{"a":0,"k":100,"ix":7},"sk":{"a":0,"k":0,"ix":4},"sa":{"a":0,"k":0,"ix":5},"nm":"Transform"}],"nm":"Group 11","np":4,"cix":2,"bm":0,"ix":11,"mn":"ADBE Vector Group","hd":false},{"ty":"gr","it":[{"ind":0,"ty":"sh","ix":1,"ks":{"a":0,"k":{"i":[[0,0],[0,0],[-3.06,-0.225],[0,0],[-0.234,3.19],[0,0],[0,0],[0,0]],"o":[[0,0],[-0.234,3.19],[0,0],[3.06,0.225],[0,0],[0,0],[0,0],[0,0]],"v":[[-20.419,-27.721],[-23.841,18.85],[-18.716,25.043],[14.679,27.496],[20.653,22.12],[22.039,3.258],[22.334,-0.754],[24.075,-24.451]],"c":true},"ix":2},"nm":"Path 1","mn":"ADBE Vector Shape - Group","hd":false},{"ty":"fl","c":{"a":0,"k":[0.861929440966,0.759610224705,0.025807326448,1],"ix":4},"o":{"a":0,"k":100,"ix":5},"r":1,"bm":0,"nm":"Fill 1","mn":"ADBE Vector Graphic - Fill","hd":false},{"ty":"tr","p":{"a":0,"k":[30.51,58.062],"ix":2},"a":{"a":0,"k":[0,0],"ix":1},"s":{"a":0,"k":[100,100],"ix":3},"r":{"a":0,"k":0,"ix":6},"o":{"a":0,"k":100,"ix":7},"sk":{"a":0,"k":0,"ix":4},"sa":{"a":0,"k":0,"ix":5},"nm":"Transform"}],"nm":"Group 12","np":4,"cix":2,"bm":0,"ix":12,"mn":"ADBE Vector Group","hd":false},{"ty":"gr","it":[{"ind":0,"ty":"sh","ix":1,"ks":{"a":0,"k":{"i":[[0,0],[-5.967,0.828],[0,0],[-5.577,-1.749],[-4.864,-3.829],[2.963,-13.543]],"o":[[0,0],[5.966,-0.827],[0,0],[0,0],[0,0],[0,0]],"v":[[-23.05,6.395],[-18.38,-3.643],[-10.07,-2.083],[1.266,-5.675],[13.428,-5.186],[21.385,9.015]],"c":true},"ix":2},"nm":"Path 1","mn":"ADBE Vector Shape - Group","hd":false},{"ty":"fl","c":{"a":0,"k":[0.999999940162,0.999999940162,1,1],"ix":4},"o":{"a":0,"k":100,"ix":5},"r":1,"bm":0,"nm":"Fill 1","mn":"ADBE Vector Graphic - Fill","hd":false},{"ty":"tr","p":{"a":0,"k":[33.176,24.38],"ix":2},"a":{"a":0,"k":[0,0],"ix":1},"s":{"a":0,"k":[100,100],"ix":3},"r":{"a":0,"k":0,"ix":6},"o":{"a":0,"k":100,"ix":7},"sk":{"a":0,"k":0,"ix":4},"sa":{"a":0,"k":0,"ix":5},"nm":"Transform"}],"nm":"Group 13","np":4,"cix":2,"bm":0,"ix":13,"mn":"ADBE Vector Group","hd":false},{"ty":"gr","it":[{"ind":0,"ty":"sh","ix":1,"ks":{"a":0,"k":{"i":[[0,0],[1.566,-0.552],[0,0],[0,0],[0,0],[0.172,-2.339]],"o":[[-0.126,1.714],[0,0],[0,0],[0,0],[2.244,0.165],[0,0]],"v":[[29.009,-0.235],[26.224,3.496],[18.22,6.314],[20.039,-18.445],[26.221,-17.991],[29.98,-13.449]],"c":true},"ix":2},"nm":"Path 1","mn":"ADBE Vector Shape - Group","hd":false},{"ind":1,"ty":"sh","ix":2,"ks":{"a":0,"k":{"i":[[7.762,0.571],[0,0],[0,0],[5.114,0.376],[0,0],[0.392,-5.33],[0,0],[-5.114,-0.376],[0,0],[-0.392,5.33],[0,0],[0,0],[-0.436,5.93],[0,0]],"o":[[0,0],[0,0],[0.392,-5.33],[0,0],[-5.113,-0.376],[0,0],[-0.392,5.33],[0,0],[5.113,0.376],[0,0],[0,0],[5.415,-1.905],[0,0],[0.594,-8.091]],"v":[[26.987,-28.422],[20.806,-28.876],[21.085,-32.68],[12.535,-43.011],[-25.115,-45.778],[-35.084,-36.807],[-40.189,32.681],[-31.639,43.012],[6.011,45.778],[15.979,36.808],[17.389,17.623],[29.385,13.398],[39.016,0.5],[39.987,-12.714]],"c":true},"ix":2},"nm":"Path 2","mn":"ADBE Vector Shape - Group","hd":false},{"ty":"mm","mm":1,"nm":"Merge Paths 1","mn":"ADBE Vector Filter - Merge","hd":false},{"ty":"fl","c":{"a":0,"k":[0.808325434666,0.855714685777,0.920545510685,1],"ix":4},"o":{"a":0,"k":100,"ix":5},"r":1,"bm":0,"nm":"Fill 1","mn":"ADBE Vector Graphic - Fill","hd":false},{"ty":"tr","p":{"a":0,"k":[40.831,46.403],"ix":2},"a":{"a":0,"k":[0,0],"ix":1},"s":{"a":0,"k":[100,100],"ix":3},"r":{"a":0,"k":0,"ix":6},"o":{"a":0,"k":100,"ix":7},"sk":{"a":0,"k":0,"ix":4},"sa":{"a":0,"k":0,"ix":5},"nm":"Transform"}],"nm":"Group 14","np":6,"cix":2,"bm":0,"ix":14,"mn":"ADBE Vector Group","hd":false}],"ip":38.0000015477717,"op":367.000014948217,"st":38.0000015477717,"bm":0},{"ddd":0,"ind":9,"ty":4,"nm":"Manager Outlines","sr":1,"ks":{"o":{"a":0,"k":100,"ix":11},"r":{"a":0,"k":0,"ix":10},"p":{"a":1,"k":[{"i":{"x":0,"y":0},"o":{"x":0,"y":0},"t":27,"s":[200.004,152.195,0],"to":[0,0,0],"ti":[0,0,0]},{"i":{"x":0.667,"y":0.667},"o":{"x":0.333,"y":0.333},"t":42,"s":[200.004,152.195,0],"to":[0,0,0],"ti":[0,0,0]},{"t":49.0000019958109,"s":[200.004,152.195,0]}],"ix":2},"a":{"a":0,"k":[74.208,-20.577,0],"ix":1},"s":{"a":1,"k":[{"i":{"x":[0,0,0.667],"y":[1,1,1]},"o":{"x":[0,0,0.333],"y":[0,0,0]},"t":27,"s":[0,0,100]},{"i":{"x":[0.667,0.667,0.667],"y":[1,1,1]},"o":{"x":[0.333,0.333,0.333],"y":[0,0,0]},"t":42,"s":[105,105,100]},{"t":49.0000019958109,"s":[100,100,100]}],"ix":6}},"ao":0,"shapes":[{"ty":"gr","it":[{"ind":0,"ty":"sh","ix":1,"ks":{"a":0,"k":{"i":[[0,0],[0,0],[-0.448,0.448],[0,0.648],[0.448,0.448],[0.65,0],[0,0]],"o":[[0,0],[0.65,0],[0.448,-0.448],[0,-0.651],[-0.448,-0.448],[0,0],[0,0]],"v":[[-2.346,-0.464],[-0.028,-0.464],[1.619,-1.136],[2.292,-2.782],[1.619,-4.43],[-0.028,-5.103],[-2.346,-5.103]],"c":true},"ix":2},"nm":"Path 1","mn":"ADBE Vector Shape - Group","hd":false},{"ind":1,"ty":"sh","ix":2,"ks":{"a":0,"k":{"i":[[0,0],[0.078,-0.371],[0.309,-0.216],[0.216,0],[0.309,0.401],[0,0],[0,0],[0,0],[0.263,-0.263],[0.402,0],[0.263,0.263],[0,0.402],[0,0],[-0.262,0.263],[-0.402,0],[0,0],[-0.619,-0.262],[-0.463,-0.464],[-0.262,-0.619],[0,-0.712],[0.525,-0.82],[0.865,-0.432]],"o":[[0.217,0.342],[-0.078,0.371],[-0.309,0.155],[-0.464,0],[0,0],[0,0],[0,0],[0,0.402],[-0.262,0.263],[-0.402,0],[-0.262,-0.263],[0,0],[0,-0.402],[0.263,-0.262],[0,0],[0.71,0],[0.62,0.263],[0.463,0.463],[0.263,0.62],[0,0.989],[-0.527,0.82],[0,0]],"v":[[4.842,5.705],[5.051,6.772],[4.472,7.654],[3.684,7.886],[2.523,7.283],[-0.77,2.319],[-2.346,2.319],[-2.346,6.494],[-2.742,7.492],[-3.739,7.886],[-4.737,7.492],[-5.13,6.494],[-5.13,-6.494],[-4.737,-7.492],[-3.739,-7.886],[-0.028,-7.886],[1.966,-7.492],[3.59,-6.401],[4.68,-4.778],[5.076,-2.782],[4.286,-0.069],[2.199,1.809]],"c":true},"ix":2},"nm":"Path 2","mn":"ADBE Vector Shape - Group","hd":false},{"ty":"mm","mm":1,"nm":"Merge Paths 1","mn":"ADBE Vector Filter - Merge","hd":false},{"ty":"fl","c":{"a":0,"k":[1,0.034250420215,0.002593720193,1],"ix":4},"o":{"a":0,"k":100,"ix":5},"r":1,"bm":0,"nm":"Fill 1","mn":"ADBE Vector Graphic - Fill","hd":false},{"ty":"tr","p":{"a":0,"k":[135.264,8.202],"ix":2},"a":{"a":0,"k":[0,0],"ix":1},"s":{"a":0,"k":[100,100],"ix":3},"r":{"a":0,"k":0,"ix":6},"o":{"a":0,"k":100,"ix":7},"sk":{"a":0,"k":0,"ix":4},"sa":{"a":0,"k":0,"ix":5},"nm":"Transform"}],"nm":"Group 1","np":6,"cix":2,"bm":0,"ix":1,"mn":"ADBE Vector Group","hd":false},{"ty":"gr","it":[{"ind":0,"ty":"sh","ix":1,"ks":{"a":0,"k":{"i":[[-0.264,-0.263],[0,-0.401],[0.263,-0.263],[0.401,0],[0,0],[0.262,0.263],[0,0.402],[0,0],[-0.263,0.263],[-0.402,0],[0,0],[-0.264,-0.262],[0,-0.402],[0.263,-0.263],[0.401,0],[0,0],[0,0],[0,0],[-0.264,-0.263],[0,-0.402],[0.262,-0.262],[0.401,0],[0,0],[0,0],[0,0]],"o":[[0.263,0.263],[0,0.402],[-0.264,0.263],[0,0],[-0.402,0],[-0.263,-0.263],[0,0],[0,-0.402],[0.262,-0.262],[0,0],[0.401,0],[0.263,0.263],[0,0.402],[-0.264,0.263],[0,0],[0,0],[0,0],[0.401,0],[0.262,0.264],[0,0.401],[-0.264,0.264],[0,0],[0,0],[0,0],[0.401,0]],"v":[[4.709,5.497],[5.103,6.494],[4.709,7.492],[3.711,7.886],[-3.711,7.886],[-4.708,7.492],[-5.103,6.494],[-5.103,-6.494],[-4.708,-7.492],[-3.711,-7.886],[3.711,-7.886],[4.709,-7.492],[5.103,-6.494],[4.709,-5.496],[3.711,-5.103],[-2.319,-5.103],[-2.319,-1.391],[0.928,-1.391],[1.926,-0.997],[2.319,0.001],[1.926,0.997],[0.928,1.393],[-2.319,1.393],[-2.319,5.102],[3.711,5.102]],"c":true},"ix":2},"nm":"Path 1","mn":"ADBE Vector Shape - Group","hd":false},{"ty":"fl","c":{"a":0,"k":[1,0.034250420215,0.002593720193,1],"ix":4},"o":{"a":0,"k":100,"ix":5},"r":1,"bm":0,"nm":"Fill 1","mn":"ADBE Vector Graphic - Fill","hd":false},{"ty":"tr","p":{"a":0,"k":[113.435,8.202],"ix":2},"a":{"a":0,"k":[0,0],"ix":1},"s":{"a":0,"k":[100,100],"ix":3},"r":{"a":0,"k":0,"ix":6},"o":{"a":0,"k":100,"ix":7},"sk":{"a":0,"k":0,"ix":4},"sa":{"a":0,"k":0,"ix":5},"nm":"Transform"}],"nm":"Group 2","np":4,"cix":2,"bm":0,"ix":2,"mn":"ADBE Vector Group","hd":false},{"ty":"gr","it":[{"ind":0,"ty":"sh","ix":1,"ks":{"a":0,"k":{"i":[[-0.264,-0.263],[0,-0.401],[0,0],[0.262,-0.619],[0.464,-0.463],[0.618,-0.263],[0.71,0],[0.619,0.262],[0.464,0.464],[0.262,0.618],[0,0.711],[0,0],[-0.263,0.62],[-0.464,0.464],[-0.618,0.264],[-0.713,0],[-0.62,-0.262],[-0.463,-0.464],[-0.264,-0.618],[0,-0.712],[0.262,-0.262],[0.401,0],[0.262,0.264],[0,0.401],[0.448,0.448],[0.648,0],[0.449,-0.449],[0,-0.65],[0,0],[-0.448,-0.449],[-0.65,0],[-0.449,0.447],[0,0.649],[0,0],[0,0],[0.263,0.263],[0,0.402],[-0.262,0.263],[-0.403,0],[0,0]],"o":[[0.262,0.263],[0,0],[0,0.711],[-0.264,0.618],[-0.463,0.464],[-0.62,0.262],[-0.713,0],[-0.618,-0.263],[-0.464,-0.463],[-0.263,-0.619],[0,0],[0,-0.712],[0.262,-0.618],[0.464,-0.464],[0.619,-0.262],[0.71,0],[0.618,0.264],[0.464,0.464],[0.262,0.62],[0,0.401],[-0.264,0.264],[-0.402,0],[-0.263,-0.262],[0,-0.65],[-0.449,-0.449],[-0.65,0],[-0.448,0.448],[0,0],[0,0.649],[0.449,0.447],[0.648,0],[0.448,-0.449],[0,0],[0,0],[-0.403,0],[-0.262,-0.263],[0,-0.401],[0.263,-0.263],[0,0],[0.401,0]],"v":[[4.709,-0.07],[5.103,0.928],[5.103,2.783],[4.709,4.779],[3.618,6.402],[1.995,7.492],[0.001,7.885],[-1.995,7.492],[-3.618,6.402],[-4.708,4.779],[-5.103,2.783],[-5.103,-2.783],[-4.708,-4.779],[-3.618,-6.402],[-1.995,-7.492],[0.001,-7.885],[1.995,-7.492],[3.618,-6.402],[4.709,-4.779],[5.103,-2.783],[4.709,-1.786],[3.711,-1.391],[2.714,-1.786],[2.319,-2.783],[1.647,-4.43],[0.001,-5.102],[-1.647,-4.43],[-2.319,-2.783],[-2.319,2.783],[-1.647,4.43],[0.001,5.102],[1.647,4.43],[2.319,2.783],[2.319,2.32],[0.928,2.32],[-0.07,1.926],[-0.464,0.928],[-0.07,-0.07],[0.928,-0.464],[3.711,-0.464]],"c":true},"ix":2},"nm":"Path 1","mn":"ADBE Vector Shape - Group","hd":false},{"ty":"fl","c":{"a":0,"k":[1,0.034250420215,0.002593720193,1],"ix":4},"o":{"a":0,"k":100,"ix":5},"r":1,"bm":0,"nm":"Fill 1","mn":"ADBE Vector Graphic - Fill","hd":false},{"ty":"tr","p":{"a":0,"k":[91.634,8.202],"ix":2},"a":{"a":0,"k":[0,0],"ix":1},"s":{"a":0,"k":[100,100],"ix":3},"r":{"a":0,"k":0,"ix":6},"o":{"a":0,"k":100,"ix":7},"sk":{"a":0,"k":0,"ix":4},"sa":{"a":0,"k":0,"ix":5},"nm":"Transform"}],"nm":"Group 3","np":4,"cix":2,"bm":0,"ix":3,"mn":"ADBE Vector Group","hd":false},{"ty":"gr","it":[{"ind":0,"ty":"sh","ix":1,"ks":{"a":0,"k":{"i":[[0,0],[0,0],[0,0]],"o":[[0,0],[0,0],[0,0]],"v":[[0.789,1.416],[0.001,-1.414],[-0.788,1.416]],"c":true},"ix":2},"nm":"Path 1","mn":"ADBE Vector Shape - Group","hd":false},{"ind":1,"ty":"sh","ix":2,"ks":{"a":0,"k":{"i":[[0,0],[0.185,-0.326],[0.372,-0.123],[0.155,0],[0.216,0.68],[0,0],[0,0],[0,0],[0.68,0],[0.061,0.032],[0.185,0.325],[-0.092,0.371],[0,0],[-0.324,0.186],[-0.37,-0.093],[-0.186,-0.494]],"o":[[0.092,0.371],[-0.186,0.325],[-0.093,0.032],[-0.681,0],[0,0],[0,0],[0,0],[-0.217,0.68],[-0.186,0],[-0.371,-0.123],[-0.186,-0.326],[0,0],[0.123,-0.37],[0.325,-0.185],[0.464,0.155],[0,0]],"v":[[5.057,6.147],[4.917,7.191],[4.082,7.863],[3.711,7.909],[2.366,6.889],[1.577,4.198],[-1.624,4.198],[-2.365,6.889],[-3.711,7.909],[-4.082,7.863],[-4.917,7.191],[-5.056,6.147],[-1.345,-6.842],[-0.673,-7.677],[0.37,-7.816],[1.345,-6.842]],"c":true},"ix":2},"nm":"Path 2","mn":"ADBE Vector Shape - Group","hd":false},{"ty":"mm","mm":1,"nm":"Merge Paths 1","mn":"ADBE Vector Filter - Merge","hd":false},{"ty":"fl","c":{"a":0,"k":[1,0.034250420215,0.002593720193,1],"ix":4},"o":{"a":0,"k":100,"ix":5},"r":1,"bm":0,"nm":"Fill 1","mn":"ADBE Vector Graphic - Fill","hd":false},{"ty":"tr","p":{"a":0,"k":[70.759,8.179],"ix":2},"a":{"a":0,"k":[0,0],"ix":1},"s":{"a":0,"k":[100,100],"ix":3},"r":{"a":0,"k":0,"ix":6},"o":{"a":0,"k":100,"ix":7},"sk":{"a":0,"k":0,"ix":4},"sa":{"a":0,"k":0,"ix":5},"nm":"Transform"}],"nm":"Group 4","np":6,"cix":2,"bm":0,"ix":4,"mn":"ADBE Vector Group","hd":false},{"ty":"gr","it":[{"ind":0,"ty":"sh","ix":1,"ks":{"a":0,"k":{"i":[[-0.403,0],[-0.264,-0.262],[0,-0.402],[0,0],[0.262,-0.263],[0.401,0],[0.248,0.464],[0,0],[0,0],[0.262,-0.263],[0.401,0],[0.262,0.263],[0,0.402],[0,0],[-0.264,0.263],[-0.403,0],[-0.248,-0.465],[0,0],[0,0],[-0.263,0.263]],"o":[[0.401,0],[0.262,0.263],[0,0],[0,0.402],[-0.264,0.263],[-0.557,0],[0,0],[0,0],[0,0.402],[-0.263,0.263],[-0.403,0],[-0.264,-0.263],[0,0],[0,-0.402],[0.262,-0.262],[0.557,0],[0,0],[0,0],[0,-0.402],[0.263,-0.262]],"v":[[3.711,-7.885],[4.709,-7.492],[5.103,-6.493],[5.103,6.495],[4.709,7.493],[3.711,7.885],[2.504,7.191],[-2.319,-1.251],[-2.319,6.495],[-2.714,7.493],[-3.711,7.885],[-4.708,7.493],[-5.103,6.495],[-5.103,-6.493],[-4.708,-7.492],[-3.711,-7.885],[-2.505,-7.189],[2.319,1.253],[2.319,-6.493],[2.713,-7.492]],"c":true},"ix":2},"nm":"Path 1","mn":"ADBE Vector Shape - Group","hd":false},{"ty":"fl","c":{"a":0,"k":[1,0.034250420215,0.002593720193,1],"ix":4},"o":{"a":0,"k":100,"ix":5},"r":1,"bm":0,"nm":"Fill 1","mn":"ADBE Vector Graphic - Fill","hd":false},{"ty":"tr","p":{"a":0,"k":[48.956,8.202],"ix":2},"a":{"a":0,"k":[0,0],"ix":1},"s":{"a":0,"k":[100,100],"ix":3},"r":{"a":0,"k":0,"ix":6},"o":{"a":0,"k":100,"ix":7},"sk":{"a":0,"k":0,"ix":4},"sa":{"a":0,"k":0,"ix":5},"nm":"Transform"}],"nm":"Group 5","np":4,"cix":2,"bm":0,"ix":5,"mn":"ADBE Vector Group","hd":false},{"ty":"gr","it":[{"ind":0,"ty":"sh","ix":1,"ks":{"a":0,"k":{"i":[[0,0],[0,0],[0,0]],"o":[[0,0],[0,0],[0,0]],"v":[[0.789,1.416],[0,-1.414],[-0.788,1.416]],"c":true},"ix":2},"nm":"Path 1","mn":"ADBE Vector Shape - Group","hd":false},{"ind":1,"ty":"sh","ix":2,"ks":{"a":0,"k":{"i":[[0,0],[0.186,-0.326],[0.372,-0.123],[0.155,0],[0.216,0.68],[0,0],[0,0],[0,0],[0.681,0],[0.062,0.032],[0.186,0.325],[-0.092,0.371],[0,0],[-0.325,0.186],[-0.372,-0.093],[-0.186,-0.494]],"o":[[0.092,0.371],[-0.185,0.325],[-0.092,0.032],[-0.68,0],[0,0],[0,0],[0,0],[-0.217,0.68],[-0.185,0],[-0.371,-0.123],[-0.185,-0.326],[0,0],[0.123,-0.37],[0.325,-0.185],[0.463,0.155],[0,0]],"v":[[5.057,6.147],[4.917,7.191],[4.082,7.863],[3.711,7.909],[2.366,6.889],[1.577,4.198],[-1.623,4.198],[-2.365,6.889],[-3.711,7.909],[-4.082,7.863],[-4.917,7.191],[-5.056,6.147],[-1.345,-6.842],[-0.673,-7.677],[0.372,-7.816],[1.346,-6.842]],"c":true},"ix":2},"nm":"Path 2","mn":"ADBE Vector Shape - Group","hd":false},{"ty":"mm","mm":1,"nm":"Merge Paths 1","mn":"ADBE Vector Filter - Merge","hd":false},{"ty":"fl","c":{"a":0,"k":[1,0.034250420215,0.002593720193,1],"ix":4},"o":{"a":0,"k":100,"ix":5},"r":1,"bm":0,"nm":"Fill 1","mn":"ADBE Vector Graphic - Fill","hd":false},{"ty":"tr","p":{"a":0,"k":[27.154,8.179],"ix":2},"a":{"a":0,"k":[0,0],"ix":1},"s":{"a":0,"k":[100,100],"ix":3},"r":{"a":0,"k":0,"ix":6},"o":{"a":0,"k":100,"ix":7},"sk":{"a":0,"k":0,"ix":4},"sa":{"a":0,"k":0,"ix":5},"nm":"Transform"}],"nm":"Group 6","np":6,"cix":2,"bm":0,"ix":6,"mn":"ADBE Vector Group","hd":false},{"ty":"gr","it":[{"ind":0,"ty":"sh","ix":1,"ks":{"a":0,"k":{"i":[[-0.309,0],[-0.264,-0.262],[0,-0.402],[0,0],[0.262,-0.263],[0.401,0],[0.262,0.263],[0,0.402],[0,0],[0,0],[0.619,0],[0.186,0.063],[0.155,0.371],[0,0],[0,0],[0.263,-0.263],[0.401,0],[0.262,0.263],[0,0.402],[0,0],[-0.263,0.263],[-0.402,0],[-0.217,-0.17],[-0.124,-0.248],[0,0],[0,0],[-0.216,0.171]],"o":[[0.401,0],[0.262,0.263],[0,0],[0,0.402],[-0.264,0.263],[-0.402,0],[-0.263,-0.263],[0,0],[0,0],[-0.248,0.588],[-0.155,0],[-0.371,-0.155],[0,0],[0,0],[0,0.402],[-0.262,0.263],[-0.402,0],[-0.263,-0.263],[0,0],[0,-0.402],[0.262,-0.262],[0.309,0],[0.216,0.171],[0,0],[0,0],[0.123,-0.248],[0.217,-0.17]],"v":[[3.711,-7.885],[4.708,-7.492],[5.103,-6.493],[5.103,6.495],[4.708,7.493],[3.711,7.885],[2.714,7.493],[2.318,6.495],[2.318,0.743],[1.299,3.294],[-0.001,4.176],[-0.511,4.083],[-1.3,3.294],[-2.32,0.743],[-2.32,6.495],[-2.715,7.493],[-3.712,7.885],[-4.709,7.493],[-5.103,6.495],[-5.103,-6.493],[-4.709,-7.492],[-3.712,-7.885],[-2.923,-7.63],[-2.413,-7.003],[-0.001,-0.973],[2.411,-7.003],[2.922,-7.63]],"c":true},"ix":2},"nm":"Path 1","mn":"ADBE Vector Shape - Group","hd":false},{"ty":"fl","c":{"a":0,"k":[1,0.034250420215,0.002593720193,1],"ix":4},"o":{"a":0,"k":100,"ix":5},"r":1,"bm":0,"nm":"Fill 1","mn":"ADBE Vector Graphic - Fill","hd":false},{"ty":"tr","p":{"a":0,"k":[5.353,8.202],"ix":2},"a":{"a":0,"k":[0,0],"ix":1},"s":{"a":0,"k":[100,100],"ix":3},"r":{"a":0,"k":0,"ix":6},"o":{"a":0,"k":100,"ix":7},"sk":{"a":0,"k":0,"ix":4},"sa":{"a":0,"k":0,"ix":5},"nm":"Transform"}],"nm":"Group 7","np":4,"cix":2,"bm":0,"ix":7,"mn":"ADBE Vector Group","hd":false},{"ty":"gr","it":[{"ind":0,"ty":"sh","ix":1,"ks":{"a":0,"k":{"i":[[0,0],[0,0],[0,0],[0.68,0],[0.067,0.028],[-0.326,-0.122],[-0.185,0],[-0.217,0.764],[0,0],[0,0]],"o":[[0,0],[0,0],[-0.217,0.765],[-0.166,0],[0.183,0.295],[0.061,0.035],[0.68,0],[0,0],[0,0],[0,0]],"v":[[2.731,-2.411],[-0.471,-2.411],[-1.213,0.615],[-2.558,1.762],[-2.9,1.719],[-2.151,2.359],[-1.781,2.411],[-0.435,1.264],[0.307,-1.762],[2.9,-1.762]],"c":true},"ix":2},"nm":"Path 1","mn":"ADBE Vector Shape - Group","hd":false},{"ty":"fl","c":{"a":0,"k":[0.808325434666,0.855714685777,0.920545510685,1],"ix":4},"o":{"a":0,"k":100,"ix":5},"r":1,"bm":0,"nm":"Fill 1","mn":"ADBE Vector Graphic - Fill","hd":false},{"ty":"tr","p":{"a":0,"k":[69.911,15.526],"ix":2},"a":{"a":0,"k":[0,0],"ix":1},"s":{"a":0,"k":[100,100],"ix":3},"r":{"a":0,"k":0,"ix":6},"o":{"a":0,"k":100,"ix":7},"sk":{"a":0,"k":0,"ix":4},"sa":{"a":0,"k":0,"ix":5},"nm":"Transform"}],"nm":"Group 8","np":4,"cix":2,"bm":0,"ix":8,"mn":"ADBE Vector Group","hd":false},{"ty":"gr","it":[{"ind":0,"ty":"sh","ix":1,"ks":{"a":0,"k":{"i":[[0.229,0.067],[0,-0.324],[0,0],[0.263,-0.695],[0.464,-0.521],[0.618,-0.295],[0.711,0],[0.618,0.295],[0.208,0.141],[-0.537,-0.256],[-0.712,0],[-0.619,0.295],[-0.463,0.521],[-0.263,0.696],[0,0.801],[0,0],[0.262,0.295]],"o":[[0.136,0.244],[0,0],[0,0.801],[-0.263,0.695],[-0.464,0.522],[-0.62,0.295],[-0.712,0],[-0.23,-0.11],[0.42,0.426],[0.618,0.295],[0.71,0],[0.619,-0.295],[0.463,-0.522],[0.262,-0.695],[0,0],[0,-0.451],[-0.171,-0.192]],"v":[[3.256,-4.656],[3.484,-3.818],[3.484,-1.731],[3.089,0.512],[1.999,2.337],[0.376,3.564],[-1.619,4.007],[-3.615,3.564],[-4.26,3.172],[-2.837,4.212],[-0.841,4.656],[1.152,4.212],[2.777,2.986],[3.867,1.161],[4.26,-1.083],[4.26,-3.169],[3.867,-4.29]],"c":true},"ix":2},"nm":"Path 1","mn":"ADBE Vector Shape - Group","hd":false},{"ty":"fl","c":{"a":0,"k":[0.808325434666,0.855714685777,0.920545510685,1],"ix":4},"o":{"a":0,"k":100,"ix":5},"r":1,"bm":0,"nm":"Fill 1","mn":"ADBE Vector Graphic - Fill","hd":false},{"ty":"tr","p":{"a":0,"k":[93.559,13.281],"ix":2},"a":{"a":0,"k":[0,0],"ix":1},"s":{"a":0,"k":[100,100],"ix":3},"r":{"a":0,"k":0,"ix":6},"o":{"a":0,"k":100,"ix":7},"sk":{"a":0,"k":0,"ix":4},"sa":{"a":0,"k":0,"ix":5},"nm":"Transform"}],"nm":"Group 9","np":4,"cix":2,"bm":0,"ix":9,"mn":"ADBE Vector Group","hd":false},{"ty":"gr","it":[{"ind":0,"ty":"sh","ix":1,"ks":{"a":0,"k":{"i":[[0,0],[0,0],[0,0],[0.68,0],[0.067,0.028],[-0.325,-0.122],[-0.186,0],[-0.217,0.764],[0,0],[0,0]],"o":[[0,0],[0,0],[-0.218,0.765],[-0.166,0],[0.182,0.295],[0.061,0.035],[0.68,0],[0,0],[0,0],[0,0]],"v":[[2.73,-2.411],[-0.47,-2.411],[-1.212,0.615],[-2.558,1.762],[-2.899,1.719],[-2.151,2.359],[-1.78,2.411],[-0.435,1.264],[0.307,-1.762],[2.899,-1.762]],"c":true},"ix":2},"nm":"Path 1","mn":"ADBE Vector Shape - Group","hd":false},{"ty":"fl","c":{"a":0,"k":[0.808325434666,0.855714685777,0.920545510685,1],"ix":4},"o":{"a":0,"k":100,"ix":5},"r":1,"bm":0,"nm":"Fill 1","mn":"ADBE Vector Graphic - Fill","hd":false},{"ty":"tr","p":{"a":0,"k":[26.307,15.526],"ix":2},"a":{"a":0,"k":[0,0],"ix":1},"s":{"a":0,"k":[100,100],"ix":3},"r":{"a":0,"k":0,"ix":6},"o":{"a":0,"k":100,"ix":7},"sk":{"a":0,"k":0,"ix":4},"sa":{"a":0,"k":0,"ix":5},"nm":"Transform"}],"nm":"Group 10","np":4,"cix":2,"bm":0,"ix":10,"mn":"ADBE Vector Group","hd":false},{"ty":"gr","it":[{"ind":0,"ty":"sh","ix":1,"ks":{"a":0,"k":{"i":[[0,0],[0.464,0.174],[0.006,0.001],[-0.057,-0.169],[0,0],[0.186,-0.366],[0.371,-0.139],[0.154,0],[0.121,0.033],[-0.532,0],[-0.092,0.035],[-0.185,0.366],[0.093,0.417]],"o":[[-0.185,-0.556],[-0.005,-0.002],[0.082,0.134],[0,0],[0.092,0.417],[-0.185,0.364],[-0.092,0.035],[-0.141,0],[0.248,0.467],[0.154,0],[0.371,-0.138],[0.185,-0.366],[0,0]],"v":[[-1.407,-7.744],[-2.381,-8.84],[-2.397,-8.841],[-2.184,-8.392],[1.527,6.212],[1.387,7.386],[0.552,8.142],[0.181,8.194],[-0.206,8.134],[0.959,8.842],[1.33,8.79],[2.165,8.034],[2.304,6.86]],"c":true},"ix":2},"nm":"Path 1","mn":"ADBE Vector Shape - Group","hd":false},{"ty":"fl","c":{"a":0,"k":[0.808325434666,0.855714685777,0.920545510685,1],"ix":4},"o":{"a":0,"k":100,"ix":5},"r":1,"bm":0,"nm":"Fill 1","mn":"ADBE Vector Graphic - Fill","hd":false},{"ty":"tr","p":{"a":0,"k":[30.989,9.095],"ix":2},"a":{"a":0,"k":[0,0],"ix":1},"s":{"a":0,"k":[100,100],"ix":3},"r":{"a":0,"k":0,"ix":6},"o":{"a":0,"k":100,"ix":7},"sk":{"a":0,"k":0,"ix":4},"sa":{"a":0,"k":0,"ix":5},"nm":"Transform"}],"nm":"Group 11","np":4,"cix":2,"bm":0,"ix":11,"mn":"ADBE Vector Group","hd":false},{"ty":"gr","it":[{"ind":0,"ty":"sh","ix":1,"ks":{"a":0,"k":{"i":[[0,0],[0,0],[0.263,-0.295],[0.402,0],[0.124,0.037],[-0.075,-0.084],[-0.402,0],[-0.262,0.295],[0,0.453],[0,0]],"o":[[0,0],[0,0.452],[-0.262,0.295],[-0.141,0],[0.053,0.096],[0.262,0.295],[0.402,0],[0.263,-0.294],[0,0],[0,0]],"v":[[0.5,-5.462],[0.5,3.249],[0.105,4.37],[-0.892,4.812],[-1.278,4.734],[-1.111,5.018],[-0.114,5.462],[0.883,5.018],[1.278,3.896],[1.278,-3.932]],"c":true},"ix":2},"nm":"Path 1","mn":"ADBE Vector Shape - Group","hd":false},{"ty":"fl","c":{"a":0,"k":[0.808325434666,0.855714685777,0.920545510685,1],"ix":4},"o":{"a":0,"k":100,"ix":5},"r":1,"bm":0,"nm":"Fill 1","mn":"ADBE Vector Graphic - Fill","hd":false},{"ty":"tr","p":{"a":0,"k":[46.442,12.475],"ix":2},"a":{"a":0,"k":[0,0],"ix":1},"s":{"a":0,"k":[100,100],"ix":3},"r":{"a":0,"k":0,"ix":6},"o":{"a":0,"k":100,"ix":7},"sk":{"a":0,"k":0,"ix":4},"sa":{"a":0,"k":0,"ix":5},"nm":"Transform"}],"nm":"Group 12","np":4,"cix":2,"bm":0,"ix":12,"mn":"ADBE Vector Group","hd":false},{"ty":"gr","it":[{"ind":0,"ty":"sh","ix":1,"ks":{"a":0,"k":{"i":[[0.229,0.067],[0,-0.324],[0,0],[0.262,-0.294],[0.402,0],[0.116,0.03],[-0.522,0],[-0.263,0.295],[0,0.452],[0,0],[0.262,0.297]],"o":[[0.135,0.245],[0,0],[0,0.453],[-0.263,0.295],[-0.134,0],[0.25,0.457],[0.402,0],[0.262,-0.295],[0,0],[0,-0.451],[-0.171,-0.191]],"v":[[0.267,-8.828],[0.494,-7.989],[0.494,6.615],[0.1,7.736],[-0.898,8.18],[-1.272,8.133],[-0.12,8.828],[0.878,8.386],[1.272,7.264],[1.272,-7.341],[0.878,-8.463]],"c":true},"ix":2},"nm":"Path 1","mn":"ADBE Vector Shape - Group","hd":false},{"ty":"fl","c":{"a":0,"k":[0.808325434666,0.855714685777,0.920545510685,1],"ix":4},"o":{"a":0,"k":100,"ix":5},"r":1,"bm":0,"nm":"Fill 1","mn":"ADBE Vector Graphic - Fill","hd":false},{"ty":"tr","p":{"a":0,"k":[53.87,9.108],"ix":2},"a":{"a":0,"k":[0,0],"ix":1},"s":{"a":0,"k":[100,100],"ix":3},"r":{"a":0,"k":0,"ix":6},"o":{"a":0,"k":100,"ix":7},"sk":{"a":0,"k":0,"ix":4},"sa":{"a":0,"k":0,"ix":5},"nm":"Transform"}],"nm":"Group 13","np":4,"cix":2,"bm":0,"ix":13,"mn":"ADBE Vector Group","hd":false},{"ty":"gr","it":[{"ind":0,"ty":"sh","ix":1,"ks":{"a":0,"k":{"i":[[0,0],[0,0],[0,0],[0.263,-0.294],[0.402,0],[0.124,0.036],[-0.075,-0.084],[-0.403,0],[-0.263,0.295],[0,0.452],[0,0],[0,0]],"o":[[0,0],[0,0],[0,0.452],[-0.263,0.295],[-0.14,0],[0.053,0.095],[0.262,0.295],[0.401,0],[0.262,-0.295],[0,0],[0,0],[0,0]],"v":[[1.486,-3.454],[-0.091,-3.454],[-0.091,1.24],[-0.485,2.361],[-1.483,2.805],[-1.869,2.728],[-1.702,3.012],[-0.704,3.454],[0.293,3.012],[0.687,1.889],[0.687,-2.805],[1.869,-2.805]],"c":true},"ix":2},"nm":"Path 1","mn":"ADBE Vector Shape - Group","hd":false},{"ty":"fl","c":{"a":0,"k":[0.808325434666,0.855714685777,0.920545510685,1],"ix":4},"o":{"a":0,"k":100,"ix":5},"r":1,"bm":0,"nm":"Fill 1","mn":"ADBE Vector Graphic - Fill","hd":false},{"ty":"tr","p":{"a":0,"k":[133.314,14.483],"ix":2},"a":{"a":0,"k":[0,0],"ix":1},"s":{"a":0,"k":[100,100],"ix":3},"r":{"a":0,"k":0,"ix":6},"o":{"a":0,"k":100,"ix":7},"sk":{"a":0,"k":0,"ix":4},"sa":{"a":0,"k":0,"ix":5},"nm":"Transform"}],"nm":"Group 14","np":4,"cix":2,"bm":0,"ix":14,"mn":"ADBE Vector Group","hd":false},{"ty":"gr","it":[{"ind":0,"ty":"sh","ix":1,"ks":{"a":0,"k":{"i":[[0,0],[-0.525,0.922],[0,1.112],[0.263,0.696],[0.463,0.52],[0.354,0.238],[-0.06,-0.068],[-0.264,-0.695],[0,-0.8],[0.526,-0.922],[0.866,-0.487],[0,0],[0.077,-0.417],[0.31,-0.243],[0.217,0],[0.13,0.044],[0,0],[-0.463,0],[-0.309,0.175],[-0.079,0.417],[0.215,0.384]],"o":[[0.866,-0.487],[0.525,-0.922],[0,-0.799],[-0.262,-0.696],[-0.291,-0.329],[0.065,0.064],[0.464,0.522],[0.263,0.697],[0,1.112],[-0.526,0.921],[0,0],[0.216,0.384],[-0.078,0.417],[-0.309,0.174],[-0.144,0],[0,0],[0.309,0.452],[0.216,0],[0.309,-0.242],[0.077,-0.417],[0,0]],"v":[[-1.076,1.617],[1.011,-0.495],[1.8,-3.548],[1.405,-5.79],[0.316,-7.615],[-0.662,-8.449],[-0.463,-8.266],[0.628,-6.439],[1.022,-4.195],[0.233,-1.145],[-1.854,0.967],[0.79,5.348],[0.999,6.549],[0.419,7.54],[-0.37,7.801],[-0.778,7.725],[-0.752,7.771],[0.408,8.449],[1.197,8.188],[1.777,7.197],[1.569,5.997]],"c":true},"ix":2},"nm":"Path 1","mn":"ADBE Vector Shape - Group","hd":false},{"ty":"fl","c":{"a":0,"k":[0.808325434666,0.855714685777,0.920545510685,1],"ix":4},"o":{"a":0,"k":100,"ix":5},"r":1,"bm":0,"nm":"Fill 1","mn":"ADBE Vector Graphic - Fill","hd":false},{"ty":"tr","p":{"a":0,"k":[139.623,9.488],"ix":2},"a":{"a":0,"k":[0,0],"ix":1},"s":{"a":0,"k":[100,100],"ix":3},"r":{"a":0,"k":0,"ix":6},"o":{"a":0,"k":100,"ix":7},"sk":{"a":0,"k":0,"ix":4},"sa":{"a":0,"k":0,"ix":5},"nm":"Transform"}],"nm":"Group 15","np":4,"cix":2,"bm":0,"ix":15,"mn":"ADBE Vector Group","hd":false},{"ty":"gr","it":[{"ind":0,"ty":"sh","ix":1,"ks":{"a":0,"k":{"i":[[0.229,0.067],[0,-0.324],[0.262,-0.295],[0.401,0],[0,0],[0.124,0.036],[-0.074,-0.084],[-0.403,0],[0,0],[-0.263,0.295],[0,0.452],[0.263,0.296]],"o":[[0.136,0.244],[0,0.452],[-0.264,0.295],[0,0],[-0.141,0],[0.053,0.096],[0.263,0.295],[0,0],[0.402,0],[0.263,-0.295],[0,-0.451],[-0.171,-0.191]],"v":[[3.984,-1.526],[4.212,-0.687],[3.818,0.434],[2.82,0.877],[-4.603,0.877],[-4.99,0.799],[-4.822,1.083],[-3.825,1.526],[3.598,1.526],[4.594,1.083],[4.99,-0.039],[4.594,-1.161]],"c":true},"ix":2},"nm":"Path 1","mn":"ADBE Vector Shape - Group","hd":false},{"ty":"fl","c":{"a":0,"k":[0.808325434666,0.855714685777,0.920545510685,1],"ix":4},"o":{"a":0,"k":100,"ix":5},"r":1,"bm":0,"nm":"Fill 1","mn":"ADBE Vector Graphic - Fill","hd":false},{"ty":"tr","p":{"a":0,"k":[114.632,16.411],"ix":2},"a":{"a":0,"k":[0,0],"ix":1},"s":{"a":0,"k":[100,100],"ix":3},"r":{"a":0,"k":0,"ix":6},"o":{"a":0,"k":100,"ix":7},"sk":{"a":0,"k":0,"ix":4},"sa":{"a":0,"k":0,"ix":5},"nm":"Transform"}],"nm":"Group 16","np":4,"cix":2,"bm":0,"ix":16,"mn":"ADBE Vector Group","hd":false},{"ty":"gr","it":[{"ind":0,"ty":"sh","ix":1,"ks":{"a":0,"k":{"i":[[0.229,0.067],[0,-0.324],[0.262,-0.295],[0.401,0],[0,0],[0,0],[0,0],[0,0],[0,0],[-0.263,0.296],[0,0.452],[0.263,0.297]],"o":[[0.136,0.245],[0,0.452],[-0.264,0.297],[0,0],[0,0],[0,0],[0,0],[0,0],[0.402,0],[0.263,-0.295],[0,-0.451],[-0.171,-0.191]],"v":[[3.094,-3.288],[3.322,-2.449],[2.928,-1.328],[1.93,-0.885],[-4.1,-0.885],[-4.1,3.288],[-3.322,3.288],[-3.322,-0.236],[2.708,-0.236],[3.705,-0.679],[4.1,-1.801],[3.705,-2.923]],"c":true},"ix":2},"nm":"Path 1","mn":"ADBE Vector Shape - Group","hd":false},{"ty":"fl","c":{"a":0,"k":[0.808325434666,0.855714685777,0.920545510685,1],"ix":4},"o":{"a":0,"k":100,"ix":5},"r":1,"bm":0,"nm":"Fill 1","mn":"ADBE Vector Graphic - Fill","hd":false},{"ty":"tr","p":{"a":0,"k":[115.521,3.568],"ix":2},"a":{"a":0,"k":[0,0],"ix":1},"s":{"a":0,"k":[100,100],"ix":3},"r":{"a":0,"k":0,"ix":6},"o":{"a":0,"k":100,"ix":7},"sk":{"a":0,"k":0,"ix":4},"sa":{"a":0,"k":0,"ix":5},"nm":"Transform"}],"nm":"Group 17","np":4,"cix":2,"bm":0,"ix":17,"mn":"ADBE Vector Group","hd":false},{"ty":"gr","it":[{"ind":0,"ty":"sh","ix":1,"ks":{"a":0,"k":{"i":[[0.464,0.521],[0.353,0.238],[-0.062,-0.069],[-0.262,-0.696],[0,-0.8],[0.263,-0.296],[0.402,0],[0.124,0.036],[-0.075,-0.083],[-0.403,0],[-0.264,0.296],[0,0.453],[0.262,0.696]],"o":[[-0.291,-0.328],[0.064,0.064],[0.464,0.521],[0.263,0.696],[0,0.451],[-0.262,0.296],[-0.14,0],[0.053,0.096],[0.261,0.296],[0.401,0],[0.262,-0.294],[0,-0.798],[-0.264,-0.695]],"v":[[-0.206,-2.401],[-1.184,-3.234],[-0.984,-3.049],[0.106,-1.224],[0.501,1.02],[0.106,2.141],[-0.892,2.583],[-1.278,2.507],[-1.111,2.788],[-0.114,3.234],[0.885,2.788],[1.278,1.667],[0.885,-0.576]],"c":true},"ix":2},"nm":"Path 1","mn":"ADBE Vector Shape - Group","hd":false},{"ty":"fl","c":{"a":0,"k":[0.808325434666,0.855714685777,0.920545510685,1],"ix":4},"o":{"a":0,"k":100,"ix":5},"r":1,"bm":0,"nm":"Fill 1","mn":"ADBE Vector Graphic - Fill","hd":false},{"ty":"tr","p":{"a":0,"k":[96.541,4.273],"ix":2},"a":{"a":0,"k":[0,0],"ix":1},"s":{"a":0,"k":[100,100],"ix":3},"r":{"a":0,"k":0,"ix":6},"o":{"a":0,"k":100,"ix":7},"sk":{"a":0,"k":0,"ix":4},"sa":{"a":0,"k":0,"ix":5},"nm":"Transform"}],"nm":"Group 18","np":4,"cix":2,"bm":0,"ix":18,"mn":"ADBE Vector Group","hd":false},{"ty":"gr","it":[{"ind":0,"ty":"sh","ix":1,"ks":{"a":0,"k":{"i":[[0,0],[0.463,0.174],[0.005,0.001],[-0.057,-0.169],[0,0],[0.185,-0.366],[0.371,-0.139],[0.154,0],[0.121,0.033],[-0.531,0],[-0.092,0.035],[-0.184,0.366],[0.093,0.417]],"o":[[-0.186,-0.556],[-0.006,-0.002],[0.082,0.134],[0,0],[0.092,0.417],[-0.186,0.364],[-0.093,0.035],[-0.142,0],[0.248,0.467],[0.155,0],[0.372,-0.138],[0.186,-0.366],[0,0]],"v":[[-1.408,-7.744],[-2.381,-8.84],[-2.397,-8.841],[-2.185,-8.392],[1.526,6.212],[1.387,7.386],[0.552,8.142],[0.181,8.194],[-0.207,8.134],[0.958,8.842],[1.329,8.79],[2.164,8.034],[2.304,6.86]],"c":true},"ix":2},"nm":"Path 1","mn":"ADBE Vector Shape - Group","hd":false},{"ty":"fl","c":{"a":0,"k":[0.808325434666,0.855714685777,0.920545510685,1],"ix":4},"o":{"a":0,"k":100,"ix":5},"r":1,"bm":0,"nm":"Fill 1","mn":"ADBE Vector Graphic - Fill","hd":false},{"ty":"tr","p":{"a":0,"k":[74.594,9.095],"ix":2},"a":{"a":0,"k":[0,0],"ix":1},"s":{"a":0,"k":[100,100],"ix":3},"r":{"a":0,"k":0,"ix":6},"o":{"a":0,"k":100,"ix":7},"sk":{"a":0,"k":0,"ix":4},"sa":{"a":0,"k":0,"ix":5},"nm":"Transform"}],"nm":"Group 19","np":4,"cix":2,"bm":0,"ix":19,"mn":"ADBE Vector Group","hd":false},{"ty":"gr","it":[{"ind":0,"ty":"sh","ix":1,"ks":{"a":0,"k":{"i":[[0.124,0.036],[-0.074,-0.083],[-0.402,0],[0,0],[0,0.045],[0,0],[0,0]],"o":[[0.053,0.096],[0.263,0.296],[0,0],[0.002,-0.044],[0,0],[0,0],[-0.142,0]],"v":[[-0.889,-0.363],[-0.722,-0.081],[0.275,0.363],[0.879,0.363],[0.889,0.236],[0.889,-0.285],[-0.502,-0.285]],"c":true},"ix":2},"nm":"Path 1","mn":"ADBE Vector Shape - Group","hd":false},{"ty":"fl","c":{"a":0,"k":[0.808325434666,0.855714685777,0.920545510685,1],"ix":4},"o":{"a":0,"k":100,"ix":5},"r":1,"bm":0,"nm":"Fill 1","mn":"ADBE Vector Graphic - Fill","hd":false},{"ty":"tr","p":{"a":0,"k":[93.369,11.315],"ix":2},"a":{"a":0,"k":[0,0],"ix":1},"s":{"a":0,"k":[100,100],"ix":3},"r":{"a":0,"k":0,"ix":6},"o":{"a":0,"k":100,"ix":7},"sk":{"a":0,"k":0,"ix":4},"sa":{"a":0,"k":0,"ix":5},"nm":"Transform"}],"nm":"Group 20","np":4,"cix":2,"bm":0,"ix":20,"mn":"ADBE Vector Group","hd":false},{"ty":"gr","it":[{"ind":0,"ty":"sh","ix":1,"ks":{"a":0,"k":{"i":[[0,0],[0,0],[0,0],[0,0]],"o":[[0,0],[0,0],[0,0],[0,0]],"v":[[0.63,0.303],[0.16,-1.591],[-0.63,1.591],[0.311,1.591]],"c":true},"ix":2},"nm":"Path 1","mn":"ADBE Vector Shape - Group","hd":false},{"ty":"fl","c":{"a":0,"k":[0.808325434666,0.855714685777,0.920545510685,1],"ix":4},"o":{"a":0,"k":100,"ix":5},"r":1,"bm":0,"nm":"Fill 1","mn":"ADBE Vector Graphic - Fill","hd":false},{"ty":"tr","p":{"a":0,"k":[70.905,8.395],"ix":2},"a":{"a":0,"k":[0,0],"ix":1},"s":{"a":0,"k":[100,100],"ix":3},"r":{"a":0,"k":0,"ix":6},"o":{"a":0,"k":100,"ix":7},"sk":{"a":0,"k":0,"ix":4},"sa":{"a":0,"k":0,"ix":5},"nm":"Transform"}],"nm":"Group 21","np":4,"cix":2,"bm":0,"ix":21,"mn":"ADBE Vector Group","hd":false},{"ty":"gr","it":[{"ind":0,"ty":"sh","ix":1,"ks":{"a":0,"k":{"i":[[0.229,0.067],[0,-0.324],[0,0],[0.263,-0.294],[0.401,0],[0.124,0.037],[-0.074,-0.084],[-0.403,0],[-0.263,0.295],[0,0.452],[0,0],[0.263,0.297]],"o":[[0.135,0.245],[0,0],[0,0.453],[-0.263,0.295],[-0.141,0],[0.053,0.095],[0.263,0.295],[0.401,0],[0.263,-0.295],[0,0],[0,-0.451],[-0.171,-0.191]],"v":[[0.273,-8.828],[0.501,-7.989],[0.501,6.615],[0.106,7.736],[-0.891,8.18],[-1.278,8.102],[-1.111,8.386],[-0.113,8.828],[0.884,8.386],[1.278,7.264],[1.278,-7.341],[0.884,-8.463]],"c":true},"ix":2},"nm":"Path 1","mn":"ADBE Vector Shape - Group","hd":false},{"ty":"fl","c":{"a":0,"k":[0.808325434666,0.855714685777,0.920545510685,1],"ix":4},"o":{"a":0,"k":100,"ix":5},"r":1,"bm":0,"nm":"Fill 1","mn":"ADBE Vector Graphic - Fill","hd":false},{"ty":"tr","p":{"a":0,"k":[10.26,9.108],"ix":2},"a":{"a":0,"k":[0,0],"ix":1},"s":{"a":0,"k":[100,100],"ix":3},"r":{"a":0,"k":0,"ix":6},"o":{"a":0,"k":100,"ix":7},"sk":{"a":0,"k":0,"ix":4},"sa":{"a":0,"k":0,"ix":5},"nm":"Transform"}],"nm":"Group 22","np":4,"cix":2,"bm":0,"ix":22,"mn":"ADBE Vector Group","hd":false},{"ty":"gr","it":[{"ind":0,"ty":"sh","ix":1,"ks":{"a":0,"k":{"i":[[0,0],[0,0],[0,0],[0,0],[-0.263,0.296],[0,0.451],[0.263,0.297],[0.23,0.067],[0,-0.326],[0.262,-0.295],[0.401,0],[0,0]],"o":[[0,0],[0,0],[0,0],[0.402,0],[0.263,-0.295],[0,-0.452],[-0.17,-0.191],[0.136,0.244],[0,0.451],[-0.264,0.296],[0,0],[0,0]],"v":[[-2.708,3.288],[-1.93,3.288],[-1.93,-0.236],[1.316,-0.236],[2.314,-0.68],[2.708,-1.801],[2.314,-2.923],[1.703,-3.288],[1.931,-2.449],[1.537,-1.329],[0.539,-0.885],[-2.708,-0.885]],"c":true},"ix":2},"nm":"Path 1","mn":"ADBE Vector Shape - Group","hd":false},{"ty":"fl","c":{"a":0,"k":[0.808325434666,0.855714685777,0.920545510685,1],"ix":4},"o":{"a":0,"k":100,"ix":5},"r":1,"bm":0,"nm":"Fill 1","mn":"ADBE Vector Graphic - Fill","hd":false},{"ty":"tr","p":{"a":0,"k":[114.129,10.871],"ix":2},"a":{"a":0,"k":[0,0],"ix":1},"s":{"a":0,"k":[100,100],"ix":3},"r":{"a":0,"k":0,"ix":6},"o":{"a":0,"k":100,"ix":7},"sk":{"a":0,"k":0,"ix":4},"sa":{"a":0,"k":0,"ix":5},"nm":"Transform"}],"nm":"Group 23","np":4,"cix":2,"bm":0,"ix":23,"mn":"ADBE Vector Group","hd":false},{"ty":"gr","it":[{"ind":0,"ty":"sh","ix":1,"ks":{"a":0,"k":{"i":[[0,0],[0,0],[-0.29,-0.145],[0.033,0.037],[0.648,0],[0,0],[0,0],[0,0]],"o":[[0,0],[0.348,0],[-0.029,-0.037],[-0.448,-0.504],[0,0],[0,0],[0,0],[0,0]],"v":[[-1.247,-1.96],[1.072,-1.96],[2.025,-1.736],[1.941,-1.852],[0.295,-2.607],[-2.025,-2.607],[-2.025,2.607],[-1.247,2.607]],"c":true},"ix":2},"nm":"Path 1","mn":"ADBE Vector Shape - Group","hd":false},{"ty":"fl","c":{"a":0,"k":[0.808325434666,0.855714685777,0.920545510685,1],"ix":4},"o":{"a":0,"k":100,"ix":5},"r":1,"bm":0,"nm":"Fill 1","mn":"ADBE Vector Graphic - Fill","hd":false},{"ty":"tr","p":{"a":0,"k":[135.248,5.292],"ix":2},"a":{"a":0,"k":[0,0],"ix":1},"s":{"a":0,"k":[100,100],"ix":3},"r":{"a":0,"k":0,"ix":6},"o":{"a":0,"k":100,"ix":7},"sk":{"a":0,"k":0,"ix":4},"sa":{"a":0,"k":0,"ix":5},"nm":"Transform"}],"nm":"Group 24","np":4,"cix":2,"bm":0,"ix":24,"mn":"ADBE Vector Group","hd":false},{"ty":"gr","it":[{"ind":0,"ty":"sh","ix":1,"ks":{"a":0,"k":{"i":[[-0.252,-0.125],[0,0.677],[0,0],[-0.448,0.504],[-0.65,0],[-0.289,-0.144],[0.031,0.036],[0.65,0],[0.449,-0.505],[0,-0.73],[0,0],[-0.448,-0.504]],"o":[[-0.386,-0.482],[0,0],[0,-0.731],[0.448,-0.504],[0.347,0],[-0.03,-0.037],[-0.45,-0.505],[-0.649,0],[-0.448,0.504],[0,0],[0,0.732],[0.209,0.234]],"v":[[-0.66,5.626],[-1.248,3.89],[-1.248,-2.369],[-0.575,-4.221],[1.072,-4.978],[2.025,-4.755],[1.942,-4.869],[0.294,-5.626],[-1.353,-4.869],[-2.025,-3.018],[-2.025,3.24],[-1.353,5.093]],"c":true},"ix":2},"nm":"Path 1","mn":"ADBE Vector Shape - Group","hd":false},{"ty":"fl","c":{"a":0,"k":[0.808325434666,0.855714685777,0.920545510685,1],"ix":4},"o":{"a":0,"k":100,"ix":5},"r":1,"bm":0,"nm":"Fill 1","mn":"ADBE Vector Graphic - Fill","hd":false},{"ty":"tr","p":{"a":0,"k":[91.645,8.31],"ix":2},"a":{"a":0,"k":[0,0],"ix":1},"s":{"a":0,"k":[100,100],"ix":3},"r":{"a":0,"k":0,"ix":6},"o":{"a":0,"k":100,"ix":7},"sk":{"a":0,"k":0,"ix":4},"sa":{"a":0,"k":0,"ix":5},"nm":"Transform"}],"nm":"Group 25","np":4,"cix":2,"bm":0,"ix":25,"mn":"ADBE Vector Group","hd":false},{"ty":"gr","it":[{"ind":0,"ty":"sh","ix":1,"ks":{"a":0,"k":{"i":[[-0.045,-0.103],[0,0],[0,0],[0,0],[0.216,0.193],[0.157,0.047]],"o":[[0,0],[0,0],[0,0],[-0.125,-0.278],[-0.125,-0.11],[0.058,0.091]],"v":[[-1.262,-3.249],[1.15,3.531],[1.424,2.764],[-0.484,-2.6],[-0.995,-3.305],[-1.424,-3.531]],"c":true},"ix":2},"nm":"Path 1","mn":"ADBE Vector Shape - Group","hd":false},{"ty":"fl","c":{"a":0,"k":[0.808325434666,0.855714685777,0.920545510685,1],"ix":4},"o":{"a":0,"k":100,"ix":5},"r":1,"bm":0,"nm":"Fill 1","mn":"ADBE Vector Graphic - Fill","hd":false},{"ty":"tr","p":{"a":0,"k":[4.508,3.795],"ix":2},"a":{"a":0,"k":[0,0],"ix":1},"s":{"a":0,"k":[100,100],"ix":3},"r":{"a":0,"k":0,"ix":6},"o":{"a":0,"k":100,"ix":7},"sk":{"a":0,"k":0,"ix":4},"sa":{"a":0,"k":0,"ix":5},"nm":"Transform"}],"nm":"Group 26","np":4,"cix":2,"bm":0,"ix":26,"mn":"ADBE Vector Group","hd":false},{"ty":"gr","it":[{"ind":0,"ty":"sh","ix":1,"ks":{"a":0,"k":{"i":[[0,0],[0,0],[0.263,-0.295],[0.402,0],[0.124,0.037],[-0.075,-0.084],[-0.403,0],[-0.263,0.295],[0,0.452],[0,0]],"o":[[0,0],[0,0.452],[-0.262,0.295],[-0.141,0],[0.053,0.096],[0.262,0.295],[0.402,0],[0.263,-0.295],[0,0],[0,0]],"v":[[0.5,-4.34],[0.5,2.128],[0.105,3.249],[-0.892,3.691],[-1.278,3.614],[-1.111,3.898],[-0.114,4.34],[0.883,3.898],[1.278,2.775],[1.278,-2.154]],"c":true},"ix":2},"nm":"Path 1","mn":"ADBE Vector Shape - Group","hd":false},{"ty":"fl","c":{"a":0,"k":[0.808325434666,0.855714685777,0.920545510685,1],"ix":4},"o":{"a":0,"k":100,"ix":5},"r":1,"bm":0,"nm":"Fill 1","mn":"ADBE Vector Graphic - Fill","hd":false},{"ty":"tr","p":{"a":0,"k":[2.838,13.596],"ix":2},"a":{"a":0,"k":[0,0],"ix":1},"s":{"a":0,"k":[100,100],"ix":3},"r":{"a":0,"k":0,"ix":6},"o":{"a":0,"k":100,"ix":7},"sk":{"a":0,"k":0,"ix":4},"sa":{"a":0,"k":0,"ix":5},"nm":"Transform"}],"nm":"Group 27","np":4,"cix":2,"bm":0,"ix":27,"mn":"ADBE Vector Group","hd":false},{"ty":"gr","it":[{"ind":0,"ty":"sh","ix":1,"ks":{"a":0,"k":{"i":[[0,0],[0,0],[0,0],[0,0]],"o":[[0,0],[0,0],[0,0],[0,0]],"v":[[0.629,0.303],[0.16,-1.591],[-0.629,1.591],[0.31,1.591]],"c":true},"ix":2},"nm":"Path 1","mn":"ADBE Vector Shape - Group","hd":false},{"ty":"fl","c":{"a":0,"k":[0.808325434666,0.855714685777,0.920545510685,1],"ix":4},"o":{"a":0,"k":100,"ix":5},"r":1,"bm":0,"nm":"Fill 1","mn":"ADBE Vector Graphic - Fill","hd":false},{"ty":"tr","p":{"a":0,"k":[27.3,8.395],"ix":2},"a":{"a":0,"k":[0,0],"ix":1},"s":{"a":0,"k":[100,100],"ix":3},"r":{"a":0,"k":0,"ix":6},"o":{"a":0,"k":100,"ix":7},"sk":{"a":0,"k":0,"ix":4},"sa":{"a":0,"k":0,"ix":5},"nm":"Transform"}],"nm":"Group 28","np":4,"cix":2,"bm":0,"ix":28,"mn":"ADBE Vector Group","hd":false},{"ty":"gr","it":[{"ind":0,"ty":"sh","ix":1,"ks":{"a":0,"k":{"i":[[-0.016,-0.033],[0,0],[0,0],[0,0],[0.366,0.095]],"o":[[0,0],[0,0],[0,0],[-0.189,-0.396],[0.016,0.031]],"v":[[-2.385,-4.702],[2.439,4.79],[2.439,3.908],[-1.607,-4.055],[-2.439,-4.79]],"c":true},"ix":2},"nm":"Path 1","mn":"ADBE Vector Shape - Group","hd":false},{"ty":"fl","c":{"a":0,"k":[0.808325434666,0.855714685777,0.920545510685,1],"ix":4},"o":{"a":0,"k":100,"ix":5},"r":1,"bm":0,"nm":"Fill 1","mn":"ADBE Vector Graphic - Fill","hd":false},{"ty":"tr","p":{"a":0,"k":[49.142,5.039],"ix":2},"a":{"a":0,"k":[0,0],"ix":1},"s":{"a":0,"k":[100,100],"ix":3},"r":{"a":0,"k":0,"ix":6},"o":{"a":0,"k":100,"ix":7},"sk":{"a":0,"k":0,"ix":4},"sa":{"a":0,"k":0,"ix":5},"nm":"Transform"}],"nm":"Group 29","np":4,"cix":2,"bm":0,"ix":29,"mn":"ADBE Vector Group","hd":false},{"ty":"gr","it":[{"ind":0,"ty":"sh","ix":1,"ks":{"a":0,"k":{"i":[[0,0],[0,0],[0.618,0],[0.126,0.036],[-0.279,-0.13],[-0.155,0],[-0.248,0.661],[0,0]],"o":[[0,0],[-0.248,0.66],[-0.111,0],[0.156,0.268],[0.186,0.072],[0.619,0],[0,0],[0,0]],"v":[[1.342,-2.254],[0.321,0.615],[-0.977,1.605],[-1.342,1.53],[-0.71,2.149],[-0.2,2.254],[1.099,1.264],[1.342,0.581]],"c":true},"ix":2},"nm":"Path 1","mn":"ADBE Vector Shape - Group","hd":false},{"ty":"fl","c":{"a":0,"k":[0.808325434666,0.855714685777,0.920545510685,1],"ix":4},"o":{"a":0,"k":100,"ix":5},"r":1,"bm":0,"nm":"Fill 1","mn":"ADBE Vector Graphic - Fill","hd":false},{"ty":"tr","p":{"a":0,"k":[6.635,11.51],"ix":2},"a":{"a":0,"k":[0,0],"ix":1},"s":{"a":0,"k":[100,100],"ix":3},"r":{"a":0,"k":0,"ix":6},"o":{"a":0,"k":100,"ix":7},"sk":{"a":0,"k":0,"ix":4},"sa":{"a":0,"k":0,"ix":5},"nm":"Transform"}],"nm":"Group 30","np":4,"cix":2,"bm":0,"ix":30,"mn":"ADBE Vector Group","hd":false}],"ip":27.0000010997325,"op":356.000014500177,"st":27.0000010997325,"bm":0},{"ddd":0,"ind":10,"ty":4,"nm":"Main Text Outlines","sr":1,"ks":{"o":{"a":0,"k":100,"ix":11},"r":{"a":0,"k":0,"ix":10},"p":{"a":1,"k":[{"i":{"x":0,"y":0},"o":{"x":0,"y":0},"t":12,"s":[200.004,191.772,0],"to":[0,0,0],"ti":[0,0,0]},{"t":27.0000010997325,"s":[200.004,191.772,0]}],"ix":2},"a":{"a":0,"k":[158,80.577,0],"ix":1},"s":{"a":1,"k":[{"i":{"x":[0,0,0.667],"y":[1,1,1]},"o":{"x":[0,0,0.333],"y":[0,0,0]},"t":12,"s":[0,0,100]},{"i":{"x":[0.667,0.667,0.667],"y":[1,1,1]},"o":{"x":[0.333,0.333,0.333],"y":[0,0,0]},"t":27,"s":[106,106,100]},{"t":31.0000012626559,"s":[100,100,100]}],"ix":6}},"ao":0,"shapes":[{"ty":"gr","it":[{"ind":0,"ty":"sh","ix":1,"ks":{"a":0,"k":{"i":[[0,0],[0,0],[0,0],[0,0],[0,0],[0,0],[0,0],[0,0],[0,0],[0,0]],"o":[[0,0],[0,0],[0,0],[0,0],[0,0],[0,0],[0,0],[0,0],[0,0],[0,0]],"v":[[-17.902,8.547],[2.187,-19.717],[8.815,-15.005],[3.018,-0.462],[11.831,-12.861],[17.902,-8.548],[-2.187,19.717],[-8.816,15.005],[-2.955,0.449],[-11.796,12.887]],"c":true},"ix":2},"nm":"Path 1","mn":"ADBE Vector Shape - Group","hd":false},{"ty":"fl","c":{"a":0,"k":[0.087090899898,0.097171125225,0.133994966395,1],"ix":4},"o":{"a":0,"k":100,"ix":5},"r":1,"bm":0,"nm":"Fill 1","mn":"ADBE Vector Graphic - Fill","hd":false},{"ty":"tr","p":{"a":0,"k":[297.695,61.721],"ix":2},"a":{"a":0,"k":[0,0],"ix":1},"s":{"a":0,"k":[100,100],"ix":3},"r":{"a":0,"k":0,"ix":6},"o":{"a":0,"k":100,"ix":7},"sk":{"a":0,"k":0,"ix":4},"sa":{"a":0,"k":0,"ix":5},"nm":"Transform"}],"nm":"Group 1","np":4,"cix":2,"bm":0,"ix":1,"mn":"ADBE Vector Group","hd":false},{"ty":"gr","it":[{"ind":0,"ty":"sh","ix":1,"ks":{"a":0,"k":{"i":[[0,0],[0.087,0.345],[0.552,0.447],[0.422,0.025],[0.346,-0.434],[0,0],[-0.244,-0.345],[-0.343,-0.262],[-0.339,0.107],[-0.216,0.262]],"o":[[0.109,-0.322],[-0.087,-0.345],[-0.402,-0.155],[-0.421,-0.026],[0,0],[-0.187,0.523],[0.244,0.344],[0.672,0.233],[0.339,-0.107],[0,0]],"v":[[6.235,-7.4],[6.268,-8.4],[5.309,-9.587],[4.073,-9.857],[2.922,-9.244],[-6.348,7.4],[-6.263,8.702],[-5.383,9.611],[-3.868,9.801],[-3.035,9.245]],"c":true},"ix":2},"nm":"Path 1","mn":"ADBE Vector Shape - Group","hd":false},{"ind":1,"ty":"sh","ix":2,"ks":{"a":0,"k":{"i":[[-0.516,0.392],[-0.61,0.219],[-0.675,-0.009],[-0.613,-0.341],[0,0],[-0.44,-0.524],[-0.224,-0.63],[0.031,-0.681],[0.356,-0.639],[0,0],[0.562,-0.384],[0.653,-0.141],[0.676,0.097],[0.584,0.325],[0,0],[0.363,0.57],[0.135,0.632],[-0.063,0.644],[-0.252,0.452],[0,0]],"o":[[0.515,-0.394],[0.61,-0.218],[0.675,0.01],[0,0],[0.584,0.326],[0.441,0.524],[0.224,0.631],[-0.03,0.68],[0,0],[-0.357,0.639],[-0.564,0.385],[-0.655,0.143],[-0.678,-0.099],[0,0],[-0.613,-0.341],[-0.364,-0.567],[-0.137,-0.633],[0.063,-0.646],[0,0],[0.251,-0.453]],"v":[[-1.335,-16.766],[0.352,-17.682],[2.279,-17.995],[4.209,-17.469],[12.191,-13.025],[13.729,-11.749],[14.726,-10.018],[15.016,-8.05],[14.437,-6.072],[2.413,15.521],[1.035,17.053],[-0.789,17.842],[-2.786,17.908],[-4.68,17.271],[-12.662,12.825],[-14.126,11.46],[-14.874,9.659],[-14.983,7.742],[-14.511,6.096],[-2.485,-15.497]],"c":true},"ix":2},"nm":"Path 2","mn":"ADBE Vector Shape - Group","hd":false},{"ty":"mm","mm":1,"nm":"Merge Paths 1","mn":"ADBE Vector Filter - Merge","hd":false},{"ty":"fl","c":{"a":0,"k":[0.087090899898,0.097171125225,0.133994966395,1],"ix":4},"o":{"a":0,"k":100,"ix":5},"r":1,"bm":0,"nm":"Fill 1","mn":"ADBE Vector Graphic - Fill","hd":false},{"ty":"tr","p":{"a":0,"k":[277.291,48.85],"ix":2},"a":{"a":0,"k":[0,0],"ix":1},"s":{"a":0,"k":[100,100],"ix":3},"r":{"a":0,"k":0,"ix":6},"o":{"a":0,"k":100,"ix":7},"sk":{"a":0,"k":0,"ix":4},"sa":{"a":0,"k":0,"ix":5},"nm":"Transform"}],"nm":"Group 2","np":6,"cix":2,"bm":0,"ix":2,"mn":"ADBE Vector Group","hd":false},{"ty":"gr","it":[{"ind":0,"ty":"sh","ix":1,"ks":{"a":0,"k":{"i":[[0,0],[0,0],[0,0],[0,0]],"o":[[0,0],[0,0],[0,0],[0,0]],"v":[[3.632,-17.418],[10.892,-14.069],[-3.632,17.418],[-10.891,14.069]],"c":true},"ix":2},"nm":"Path 1","mn":"ADBE Vector Shape - Group","hd":false},{"ty":"fl","c":{"a":0,"k":[0.087090899898,0.097171125225,0.133994966395,1],"ix":4},"o":{"a":0,"k":100,"ix":5},"r":1,"bm":0,"nm":"Fill 1","mn":"ADBE Vector Graphic - Fill","hd":false},{"ty":"tr","p":{"a":0,"k":[261.039,40.625],"ix":2},"a":{"a":0,"k":[0,0],"ix":1},"s":{"a":0,"k":[100,100],"ix":3},"r":{"a":0,"k":0,"ix":6},"o":{"a":0,"k":100,"ix":7},"sk":{"a":0,"k":0,"ix":4},"sa":{"a":0,"k":0,"ix":5},"nm":"Transform"}],"nm":"Group 3","np":4,"cix":2,"bm":0,"ix":3,"mn":"ADBE Vector Group","hd":false},{"ty":"gr","it":[{"ind":0,"ty":"sh","ix":1,"ks":{"a":0,"k":{"i":[[0,0],[0,0],[0,0],[0,0],[0,0],[0,0],[0,0],[0,0]],"o":[[0,0],[0,0],[0,0],[0,0],[0,0],[0,0],[0,0],[0,0]],"v":[[-1.828,-10.819],[-5.969,-12.396],[-3.693,-18.374],[11.89,-12.439],[9.615,-6.463],[5.43,-8.055],[-4.632,18.374],[-11.89,15.611]],"c":true},"ix":2},"nm":"Path 1","mn":"ADBE Vector Shape - Group","hd":false},{"ty":"fl","c":{"a":0,"k":[0.087090899898,0.097171125225,0.133994966395,1],"ix":4},"o":{"a":0,"k":100,"ix":5},"r":1,"bm":0,"nm":"Fill 1","mn":"ADBE Vector Graphic - Fill","hd":false},{"ty":"tr","p":{"a":0,"k":[247.66,33.334],"ix":2},"a":{"a":0,"k":[0,0],"ix":1},"s":{"a":0,"k":[100,100],"ix":3},"r":{"a":0,"k":0,"ix":6},"o":{"a":0,"k":100,"ix":7},"sk":{"a":0,"k":0,"ix":4},"sa":{"a":0,"k":0,"ix":5},"nm":"Transform"}],"nm":"Group 4","np":4,"cix":2,"bm":0,"ix":4,"mn":"ADBE Vector Group","hd":false},{"ty":"gr","it":[{"ind":0,"ty":"sh","ix":1,"ks":{"a":0,"k":{"i":[[-0.322,1.112],[0,0],[-0.248,0.421],[-0.342,0.298],[-0.424,0.146],[-0.498,-0.146],[0,0],[0,0],[0,0],[0,0],[0,0],[0,0],[0,0],[0.427,0.822]],"o":[[0,0],[0.128,-0.438],[0.249,-0.419],[0.34,-0.298],[0.422,-0.146],[0,0],[0,0],[0,0],[0,0],[0,0],[0,0],[0,0],[-0.789,-0.231],[-0.428,-0.821]],"v":[[-11.062,10.703],[-3.557,-15.138],[-2.993,-16.425],[-2.109,-17.5],[-0.963,-18.166],[0.416,-18.169],[11.385,-14.984],[9.588,-8.798],[3.226,-10.647],[-2.865,10.325],[3.497,12.173],[1.713,18.315],[-9.081,15.181],[-10.906,13.603]],"c":true},"ix":2},"nm":"Path 1","mn":"ADBE Vector Shape - Group","hd":false},{"ty":"fl","c":{"a":0,"k":[0.087090899898,0.097171125225,0.133994966395,1],"ix":4},"o":{"a":0,"k":100,"ix":5},"r":1,"bm":0,"nm":"Fill 1","mn":"ADBE Vector Graphic - Fill","hd":false},{"ty":"tr","p":{"a":0,"k":[226.906,28.096],"ix":2},"a":{"a":0,"k":[0,0],"ix":1},"s":{"a":0,"k":[100,100],"ix":3},"r":{"a":0,"k":0,"ix":6},"o":{"a":0,"k":100,"ix":7},"sk":{"a":0,"k":0,"ix":4},"sa":{"a":0,"k":0,"ix":5},"nm":"Transform"}],"nm":"Group 5","np":4,"cix":2,"bm":0,"ix":5,"mn":"ADBE Vector Group","hd":false},{"ty":"gr","it":[{"ind":0,"ty":"sh","ix":1,"ks":{"a":0,"k":{"i":[[0,0],[0,0],[0,0],[0.418,-0.538],[0.579,-0.335],[0.675,-0.113],[0.656,0.132],[0,0],[0.52,0.43],[0.323,0.561],[0.137,0.634],[-0.101,0.509],[0,0],[0,0],[0,0],[-0.338,-0.253],[-0.406,-0.143],[-0.289,0.207],[-0.126,0.317]],"o":[[0,0],[0,0],[-0.144,0.717],[-0.418,0.537],[-0.579,0.335],[-0.675,0.115],[0,0],[-0.688,-0.137],[-0.519,-0.43],[-0.325,-0.561],[-0.139,-0.632],[0,0],[0,0],[0,0],[-0.017,0.555],[0.337,0.254],[0.711,0.019],[0.289,-0.206],[0,0]],"v":[[4.792,-16.183],[12.453,-14.655],[6.645,14.466],[5.803,16.349],[4.308,17.658],[2.427,18.33],[0.429,18.304],[-8.532,16.517],[-10.342,15.667],[-11.606,14.181],[-12.297,12.388],[-12.352,10.677],[-6.543,-18.445],[1.074,-16.925],[-4.181,9.42],[-3.701,10.632],[-2.586,11.228],[-1.085,10.945],[-0.462,10.161]],"c":true},"ix":2},"nm":"Path 1","mn":"ADBE Vector Shape - Group","hd":false},{"ty":"fl","c":{"a":0,"k":[0.087090899898,0.097171125225,0.133994966395,1],"ix":4},"o":{"a":0,"k":100,"ix":5},"r":1,"bm":0,"nm":"Fill 1","mn":"ADBE Vector Graphic - Fill","hd":false},{"ty":"tr","p":{"a":0,"k":[206.136,22.206],"ix":2},"a":{"a":0,"k":[0,0],"ix":1},"s":{"a":0,"k":[100,100],"ix":3},"r":{"a":0,"k":0,"ix":6},"o":{"a":0,"k":100,"ix":7},"sk":{"a":0,"k":0,"ix":4},"sa":{"a":0,"k":0,"ix":5},"nm":"Transform"}],"nm":"Group 6","np":4,"cix":2,"bm":0,"ix":6,"mn":"ADBE Vector Group","hd":false},{"ty":"gr","it":[{"ind":0,"ty":"sh","ix":1,"ks":{"a":0,"k":{"i":[[0,0],[0,0],[0,0],[0.215,0.282],[0.684,0.193],[0.397,-0.143],[0.147,-0.535]],"o":[[0,0],[0,0],[-0.026,-0.34],[-0.217,-0.282],[-0.43,0.018],[-0.398,0.143],[0,0]],"v":[[-2.025,2.839],[1.746,3.227],[3.051,-9.499],[2.688,-10.432],[1.337,-11.145],[0.096,-10.904],[-0.721,-9.887]],"c":true},"ix":2},"nm":"Path 1","mn":"ADBE Vector Shape - Group","hd":false},{"ind":1,"ty":"sh","ix":2,"ks":{"a":0,"k":{"i":[[0,0],[0,0],[-0.319,0.565],[-0.473,0.441],[-0.624,0.258],[-0.697,-0.071],[0,0],[-0.611,-0.308],[-0.454,-0.49],[-0.242,-0.637],[0.074,-0.726],[0,0],[0,0],[0,0],[0,0],[0,0]],"o":[[0,0],[0.054,-0.515],[0.317,-0.564],[0.474,-0.442],[0.623,-0.258],[0,0],[0.665,0.069],[0.612,0.308],[0.455,0.491],[0.239,0.637],[0,0],[0,0],[0,0],[0,0],[0,0],[0,0]],"v":[[-11.187,16.046],[-8.158,-13.495],[-7.601,-15.115],[-6.413,-16.622],[-4.767,-17.671],[-2.788,-17.951],[6.303,-17.018],[8.219,-16.454],[9.819,-15.258],[10.863,-13.566],[11.112,-11.52],[8.082,18.021],[0.311,17.225],[1.076,9.771],[-2.697,9.385],[-3.462,16.837]],"c":true},"ix":2},"nm":"Path 2","mn":"ADBE Vector Shape - Group","hd":false},{"ty":"mm","mm":1,"nm":"Merge Paths 1","mn":"ADBE Vector Filter - Merge","hd":false},{"ty":"fl","c":{"a":0,"k":[0.087090899898,0.097171125225,0.133994966395,1],"ix":4},"o":{"a":0,"k":100,"ix":5},"r":1,"bm":0,"nm":"Fill 1","mn":"ADBE Vector Graphic - Fill","hd":false},{"ty":"tr","p":{"a":0,"k":[181.727,19.297],"ix":2},"a":{"a":0,"k":[0,0],"ix":1},"s":{"a":0,"k":[100,100],"ix":3},"r":{"a":0,"k":0,"ix":6},"o":{"a":0,"k":100,"ix":7},"sk":{"a":0,"k":0,"ix":4},"sa":{"a":0,"k":0,"ix":5},"nm":"Transform"}],"nm":"Group 7","np":6,"cix":2,"bm":0,"ix":7,"mn":"ADBE Vector Group","hd":false},{"ty":"gr","it":[{"ind":0,"ty":"sh","ix":1,"ks":{"a":0,"k":{"i":[[0,0],[0,0],[0,0],[0,0],[0,0],[0,0],[0,0],[0,0],[0,0]],"o":[[0,0],[0,0],[0,0],[0,0],[0,0],[0,0],[0,0],[0,0],[0,0]],"v":[[-2.443,17.567],[-2.995,1.769],[-10.09,-16.862],[-2.283,-17.136],[0.521,-7.496],[2.283,-17.294],[10.09,-17.567],[4.768,1.499],[5.318,17.296]],"c":true},"ix":2},"nm":"Path 1","mn":"ADBE Vector Shape - Group","hd":false},{"ty":"fl","c":{"a":0,"k":[0.087090899898,0.097171125225,0.133994966395,1],"ix":4},"o":{"a":0,"k":100,"ix":5},"r":1,"bm":0,"nm":"Fill 1","mn":"ADBE Vector Graphic - Fill","hd":false},{"ty":"tr","p":{"a":0,"k":[143.276,17.817],"ix":2},"a":{"a":0,"k":[0,0],"ix":1},"s":{"a":0,"k":[100,100],"ix":3},"r":{"a":0,"k":0,"ix":6},"o":{"a":0,"k":100,"ix":7},"sk":{"a":0,"k":0,"ix":4},"sa":{"a":0,"k":0,"ix":5},"nm":"Transform"}],"nm":"Group 8","np":4,"cix":2,"bm":0,"ix":8,"mn":"ADBE Vector Group","hd":false},{"ty":"gr","it":[{"ind":0,"ty":"sh","ix":1,"ks":{"a":0,"k":{"i":[[0,0],[0,0],[-0.13,0.504],[0,0],[0.13,0.216],[0.252,0.066],[0,0],[0.343,0.194],[0.269,0.369],[0.172,0.472],[0.057,0.545],[0,0],[-0.52,0.73],[-1.151,0.123],[0,0],[0,0],[0,0],[0.093,-0.561],[0,0],[-0.626,-0.118],[0,0],[-0.32,-0.271],[-0.199,-0.423],[-0.111,-0.463],[-0.035,-0.334],[0,0],[0.119,-0.456],[0.236,-0.376],[0.325,-0.248],[0.332,-0.036],[0,0]],"o":[[0,0],[0.498,-0.205],[0,0],[-0.091,-0.265],[-0.13,-0.215],[0,0],[-0.425,0.045],[-0.342,-0.194],[-0.269,-0.369],[-0.173,-0.472],[0,0],[-0.1,-0.939],[0.52,-0.728],[0,0],[0,0],[0,0],[-0.435,0.23],[0,0],[0.101,0.664],[0,0],[0.485,-0.051],[0.32,0.272],[0.198,0.423],[0.11,0.464],[0,0],[0.045,0.424],[-0.12,0.457],[-0.235,0.378],[-0.327,0.25],[0,0],[0,0]],"v":[[-6.483,11.654],[0.059,10.956],[1.002,9.891],[0.412,4.348],[0.081,3.626],[-0.492,3.204],[-4.671,3.65],[-5.821,3.428],[-6.737,2.583],[-7.4,1.323],[-7.746,-0.204],[-9.112,-13.014],[-8.483,-15.517],[-5.978,-16.794],[5.879,-18.058],[6.562,-11.654],[-0.161,-10.936],[-0.953,-9.749],[-0.416,-4.707],[0.674,-3.536],[5.125,-4.01],[6.332,-3.68],[7.11,-2.637],[7.573,-1.308],[7.792,-0.114],[9.167,12.788],[9.055,14.109],[8.522,15.361],[7.681,16.299],[6.693,16.728],[-5.8,18.058]],"c":true},"ix":2},"nm":"Path 1","mn":"ADBE Vector Shape - Group","hd":false},{"ty":"fl","c":{"a":0,"k":[0.087090899898,0.097171125225,0.133994966395,1],"ix":4},"o":{"a":0,"k":100,"ix":5},"r":1,"bm":0,"nm":"Fill 1","mn":"ADBE Vector Graphic - Fill","hd":false},{"ty":"tr","p":{"a":0,"k":[122.254,19.441],"ix":2},"a":{"a":0,"k":[0,0],"ix":1},"s":{"a":0,"k":[100,100],"ix":3},"r":{"a":0,"k":0,"ix":6},"o":{"a":0,"k":100,"ix":7},"sk":{"a":0,"k":0,"ix":4},"sa":{"a":0,"k":0,"ix":5},"nm":"Transform"}],"nm":"Group 9","np":4,"cix":2,"bm":0,"ix":9,"mn":"ADBE Vector Group","hd":false},{"ty":"gr","it":[{"ind":0,"ty":"sh","ix":1,"ks":{"a":0,"k":{"i":[[0,0],[0,0],[0,0],[0.287,0.209],[0.711,-0.01],[0.34,-0.251],[-0.011,-0.555]],"o":[[0,0],[0,0],[-0.122,-0.318],[-0.288,-0.208],[-0.408,0.139],[-0.341,0.249],[0,0]],"v":[[-1.694,3.133],[2.033,2.431],[-0.336,-10.139],[-0.949,-10.93],[-2.447,-11.229],[-3.569,-10.645],[-4.062,-9.438]],"c":true},"ix":2},"nm":"Path 1","mn":"ADBE Vector Shape - Group","hd":false},{"ind":1,"ty":"sh","ix":2,"ks":{"a":0,"k":{"i":[[0,0],[0,0],[-0.144,0.631],[-0.329,0.558],[-0.524,0.425],[-0.689,0.13],[0,0],[-0.673,-0.121],[-0.575,-0.342],[-0.412,-0.541],[-0.135,-0.718],[0,0],[0,0],[0,0],[0,0],[0,0]],"o":[[0,0],[-0.096,-0.509],[0.144,-0.633],[0.329,-0.557],[0.525,-0.424],[0,0],[0.658,-0.124],[0.674,0.121],[0.576,0.341],[0.412,0.543],[0,0],[0,0],[0,0],[0,0],[0,0],[0,0]],"v":[[-6.722,18.399],[-12.218,-10.784],[-12.146,-12.494],[-11.436,-14.279],[-10.156,-15.752],[-8.336,-16.582],[0.643,-18.274],[2.641,-18.278],[4.515,-17.584],[5.996,-16.261],[6.817,-14.369],[12.314,14.814],[4.637,16.259],[3.25,8.897],[-0.477,9.598],[0.91,16.96]],"c":true},"ix":2},"nm":"Path 2","mn":"ADBE Vector Shape - Group","hd":false},{"ty":"mm","mm":1,"nm":"Merge Paths 1","mn":"ADBE Vector Filter - Merge","hd":false},{"ty":"fl","c":{"a":0,"k":[0.087090899898,0.097171125225,0.133994966395,1],"ix":4},"o":{"a":0,"k":100,"ix":5},"r":1,"bm":0,"nm":"Fill 1","mn":"ADBE Vector Graphic - Fill","hd":false},{"ty":"tr","p":{"a":0,"k":[101.027,23.051],"ix":2},"a":{"a":0,"k":[0,0],"ix":1},"s":{"a":0,"k":[100,100],"ix":3},"r":{"a":0,"k":0,"ix":6},"o":{"a":0,"k":100,"ix":7},"sk":{"a":0,"k":0,"ix":4},"sa":{"a":0,"k":0,"ix":5},"nm":"Transform"}],"nm":"Group 10","np":6,"cix":2,"bm":0,"ix":10,"mn":"ADBE Vector Group","hd":false},{"ty":"gr","it":[{"ind":0,"ty":"sh","ix":1,"ks":{"a":0,"k":{"i":[[0,0],[0,0],[0,0],[0,0],[0,0],[0,0],[0,0],[0,0]],"o":[[0,0],[0,0],[0,0],[0,0],[0,0],[0,0],[0,0],[0,0]],"v":[[-4.606,-8.84],[-8.867,-7.624],[-10.624,-13.775],[5.412,-18.352],[7.167,-12.2],[2.862,-10.973],[10.624,16.222],[3.156,18.352]],"c":true},"ix":2},"nm":"Path 1","mn":"ADBE Vector Shape - Group","hd":false},{"ty":"fl","c":{"a":0,"k":[0.087090899898,0.097171125225,0.133994966395,1],"ix":4},"o":{"a":0,"k":100,"ix":5},"r":1,"bm":0,"nm":"Fill 1","mn":"ADBE Vector Graphic - Fill","hd":false},{"ty":"tr","p":{"a":0,"k":[76.371,27.212],"ix":2},"a":{"a":0,"k":[0,0],"ix":1},"s":{"a":0,"k":[100,100],"ix":3},"r":{"a":0,"k":0,"ix":6},"o":{"a":0,"k":100,"ix":7},"sk":{"a":0,"k":0,"ix":4},"sa":{"a":0,"k":0,"ix":5},"nm":"Transform"}],"nm":"Group 11","np":4,"cix":2,"bm":0,"ix":11,"mn":"ADBE Vector Group","hd":false},{"ty":"gr","it":[{"ind":0,"ty":"sh","ix":1,"ks":{"a":0,"k":{"i":[[0,0],[0,0],[0,0],[0,0],[0,0],[0,0],[0,0],[0,0],[0,0],[0,0]],"o":[[0,0],[0,0],[0,0],[0,0],[0,0],[0,0],[0,0],[0,0],[0,0],[0,0]],"v":[[-2.516,19.677],[-15.386,-12.521],[-7.834,-15.539],[1.249,-2.786],[-4.398,-16.912],[2.517,-19.677],[15.386,12.523],[7.835,15.54],[-1.222,2.727],[4.442,16.897]],"c":true},"ix":2},"nm":"Path 1","mn":"ADBE Vector Shape - Group","hd":false},{"ty":"fl","c":{"a":0,"k":[0.087090899898,0.097171125225,0.133994966395,1],"ix":4},"o":{"a":0,"k":100,"ix":5},"r":1,"bm":0,"nm":"Fill 1","mn":"ADBE Vector Graphic - Fill","hd":false},{"ty":"tr","p":{"a":0,"k":[57.03,35.141],"ix":2},"a":{"a":0,"k":[0,0],"ix":1},"s":{"a":0,"k":[100,100],"ix":3},"r":{"a":0,"k":0,"ix":6},"o":{"a":0,"k":100,"ix":7},"sk":{"a":0,"k":0,"ix":4},"sa":{"a":0,"k":0,"ix":5},"nm":"Transform"}],"nm":"Group 12","np":4,"cix":2,"bm":0,"ix":12,"mn":"ADBE Vector Group","hd":false},{"ty":"gr","it":[{"ind":0,"ty":"sh","ix":1,"ks":{"a":0,"k":{"i":[[0,0],[0,0],[0,0],[0.338,0.11],[0.672,-0.231],[0.246,-0.343],[-0.184,-0.525]],"o":[[0,0],[0,0],[-0.214,-0.263],[-0.338,-0.109],[-0.344,0.26],[-0.245,0.344],[0,0]],"v":[[-1.046,2.859],[2.277,1.033],[-3.887,-10.178],[-4.717,-10.738],[-6.232,-10.555],[-7.118,-9.652],[-7.21,-8.35]],"c":true},"ix":2},"nm":"Path 1","mn":"ADBE Vector Shape - Group","hd":false},{"ind":1,"ty":"sh","ix":2,"ks":{"a":0,"k":{"i":[[0,0],[0,0],[0.059,0.645],[-0.139,0.634],[-0.367,0.567],[-0.613,0.339],[0,0],[-0.678,0.094],[-0.654,-0.144],[-0.561,-0.386],[-0.351,-0.64],[0,0],[0,0],[0,0],[0,0],[0,0]],"o":[[0,0],[-0.249,-0.453],[-0.059,-0.646],[0.138,-0.631],[0.366,-0.566],[0,0],[0.587,-0.323],[0.677,-0.095],[0.653,0.145],[0.56,0.387],[0,0],[0,0],[0,0],[0,0],[0,0],[0,0]],"v":[[-1.072,18.932],[-15.38,-7.09],[-15.844,-8.738],[-15.723,-10.656],[-14.965,-12.454],[-13.497,-13.81],[-5.49,-18.212],[-3.592,-18.837],[-1.594,-18.762],[0.225,-17.965],[1.594,-16.424],[15.902,9.598],[9.057,13.363],[5.447,6.797],[2.124,8.625],[5.734,15.189]],"c":true},"ix":2},"nm":"Path 2","mn":"ADBE Vector Shape - Group","hd":false},{"ty":"mm","mm":1,"nm":"Merge Paths 1","mn":"ADBE Vector Filter - Merge","hd":false},{"ty":"fl","c":{"a":0,"k":[0.087090899898,0.097171125225,0.133994966395,1],"ix":4},"o":{"a":0,"k":100,"ix":5},"r":1,"bm":0,"nm":"Fill 1","mn":"ADBE Vector Graphic - Fill","hd":false},{"ty":"tr","p":{"a":0,"k":[36.041,46.397],"ix":2},"a":{"a":0,"k":[0,0],"ix":1},"s":{"a":0,"k":[100,100],"ix":3},"r":{"a":0,"k":0,"ix":6},"o":{"a":0,"k":100,"ix":7},"sk":{"a":0,"k":0,"ix":4},"sa":{"a":0,"k":0,"ix":5},"nm":"Transform"}],"nm":"Group 13","np":6,"cix":2,"bm":0,"ix":13,"mn":"ADBE Vector Group","hd":false},{"ty":"gr","it":[{"ind":0,"ty":"sh","ix":1,"ks":{"a":0,"k":{"i":[[0,0],[0,0],[0,0],[0,0],[0,0],[0,0],[0,0],[0,0],[0,0],[0,0]],"o":[[0,0],[0,0],[0,0],[0,0],[0,0],[0,0],[0,0],[0,0],[0,0],[0,0]],"v":[[-13.375,-9.645],[-1.505,-18.333],[2.273,-13.174],[-3.331,-9.072],[1.096,-3.027],[6.772,-7.182],[10.659,-1.874],[4.982,2.283],[13.375,13.747],[7.108,18.333]],"c":true},"ix":2},"nm":"Path 1","mn":"ADBE Vector Shape - Group","hd":false},{"ty":"fl","c":{"a":0,"k":[0.087090899898,0.097171125225,0.133994966395,1],"ix":4},"o":{"a":0,"k":100,"ix":5},"r":1,"bm":0,"nm":"Fill 1","mn":"ADBE Vector Graphic - Fill","hd":false},{"ty":"tr","p":{"a":0,"k":[13.625,57.326],"ix":2},"a":{"a":0,"k":[0,0],"ix":1},"s":{"a":0,"k":[100,100],"ix":3},"r":{"a":0,"k":0,"ix":6},"o":{"a":0,"k":100,"ix":7},"sk":{"a":0,"k":0,"ix":4},"sa":{"a":0,"k":0,"ix":5},"nm":"Transform"}],"nm":"Group 14","np":2,"cix":2,"bm":0,"ix":14,"mn":"ADBE Vector Group","hd":false}],"ip":12.00000048877,"op":341.000013889215,"st":12.00000048877,"bm":0}],"markers":[]}